Workbook
Name Slicer_AtriRiskCategory: #N/A
Name Slicer_Department: #N/A
Name Slicer_Gender1: #N/A
Name Slicer_JobLevel: #N/A
Name Slicer_JobRole: #N/A
Name Slicer_OverTime: #N/A

Sheet RawData
A1: Age | B1: Attrition | C1: BusinessTravel | D1: DailyRate | E1: Department | F1: DistanceFromHome | G1: Education | H1: EducationField | I1: EmployeeCount | J1: EmployeeNumber | K1: EnvironmentSatisfaction | L1: Gender | M1: HourlyRate | N1: JobInvolvement | O1: JobLevel | P1: JobRole | Q1: JobSatisfaction | R1: MaritalStatus | S1: MonthlyIncome | T1: MonthlyRate | U1: NumCompaniesWorked | V1: Over18 | W1: OverTime | X1: PercentSalaryHike | Y1: PerformanceRating | Z1: RelationshipSatisfaction | AA1: StandardHours | AB1: StockOptionLevel | AC1: TotalWorkingYears | AD1: TrainingTimesLastYear | AE1: WorkLifeBalance | AF1: YearsAtCompany | AG1: YearsInCurrentRole | AH1: YearsSinceLastPromotion | AI1: YearsWithCurrManager
A2: 41 | B2: Yes | C2: Travel_Rarely | D2: 1102 | E2: Sales | F2: 1 | G2: 2 | H2: Life Sciences | I2: 1 | J2: 1 | K2: 2 | L2: Female | M2: 94 | N2: 3 | O2: 2 | P2: Sales Executive | Q2: 4 | R2: Single | S2: 5993 | T2: 19479 | U2: 8 | V2: Y | W2: Yes | X2: 11 | Y2: 3 | Z2: 1 | AA2: 80 | AB2: 0 | AC2: 8 | AD2: 0 | AE2: 1 | AF2: 6 | AG2: 4 | AH2: 0 | AI2: 5
A3: 49 | B3: No | C3: Travel_Frequently | D3: 279 | E3: Research & Development | F3: 8 | G3: 1 | H3: Life Sciences | I3: 1 | J3: 2 | K3: 3 | L3: Male | M3: 61 | N3: 2 | O3: 2 | P3: Research Scientist | Q3: 2 | R3: Married | S3: 5130 | T3: 24907 | U3: 1 | V3: Y | W3: No | X3: 23 | Y3: 4 | Z3: 4 | AA3: 80 | AB3: 1 | AC3: 10 | AD3: 3 | AE3: 3 | AF3: 10 | AG3: 7 | AH3: 1 | AI3: 7
A4: 37 | B4: Yes | C4: Travel_Rarely | D4: 1373 | E4: Research & Development | F4: 2 | G4: 2 | H4: Other | I4: 1 | J4: 4 | K4: 4 | L4: Male | M4: 92 | N4: 2 | O4: 1 | P4: Laboratory Technician | Q4: 3 | R4: Single | S4: 2090 | T4: 2396 | U4: 6 | V4: Y | W4: Yes | X4: 15 | Y4: 3 | Z4: 2 | AA4: 80 | AB4: 0 | AC4: 7 | AD4: 3 | AE4: 3 | AF4: 0 | AG4: 0 | AH4: 0 | AI4: 0
A5: 33 | B5: No | C5: Travel_Frequently | D5: 1392 | E5: Research & Development | F5: 3 | G5: 4 | H5: Life Sciences | I5: 1 | J5: 5 | K5: 4 | L5: Female | M5: 56 | N5: 3 | O5: 1 | P5: Research Scientist | Q5: 3 | R5: Married | S5: 2909 | T5: 23159 | U5: 1 | V5: Y | W5: Yes | X5: 11 | Y5: 3 | Z5: 3 | AA5: 80 | AB5: 0 | AC5: 8 | AD5: 3 | AE5: 3 | AF5: 8 | AG5: 7 | AH5: 3 | AI5: 0
A6: 27 | B6: No | C6: Travel_Rarely | D6: 591 | E6: Research & Development | F6: 2 | G6: 1 | H6: Medical | I6: 1 | J6: 7 | K6: 1 | L6: Male | M6: 40 | N6: 3 | O6: 1 | P6: Laboratory Technician | Q6: 2 | R6: Married | S6: 3468 | T6: 16632 | U6: 9 | V6: Y | W6: No | X6: 12 | Y6: 3 | Z6: 4 | AA6: 80 | AB6: 1 | AC6: 6 | AD6: 3 | AE6: 3 | AF6: 2 | AG6: 2 | AH6: 2 | AI6: 2
A7: 32 | B7: No | C7: Travel_Frequently | D7: 1005 | E7: Research & Development | F7: 2 | G7: 2 | H7: Life Sciences | I7: 1 | J7: 8 | K7: 4 | L7: Male | M7: 79 | N7: 3 | O7: 1 | P7: Laboratory Technician | Q7: 4 | R7: Single | S7: 3068 | T7: 11864 | U7: 0 | V7: Y | W7: No | X7: 13 | Y7: 3 | Z7: 3 | AA7: 80 | AB7: 0 | AC7: 8 | AD7: 2 | AE7: 2 | AF7: 7 | AG7: 7 | AH7: 3 | AI7: 6
A8: 59 | B8: No | C8: Travel_Rarely | D8: 1324 | E8: Research & Development | F8: 3 | G8: 3 | H8: Medical | I8: 1 | J8: 10 | K8: 3 | L8: Female | M8: 81 | N8: 4 | O8: 1 | P8: Laboratory Technician | Q8: 1 | R8: Married | S8: 2670 | T8: 9964 | U8: 4 | V8: Y | W8: Yes | X8: 20 | Y8: 4 | Z8: 1 | AA8: 80 | AB8: 3 | AC8: 12 | AD8: 3 | AE8: 2 | AF8: 1 | AG8: 0 | AH8: 0 | AI8: 0
A9: 30 | B9: No | C9: Travel_Rarely | D9: 1358 | E9: Research & Development | F9: 24 | G9: 1 | H9: Life Sciences | I9: 1 | J9: 11 | K9: 4 | L9: Male | M9: 67 | N9: 3 | O9: 1 | P9: Laboratory Technician | Q9: 3 | R9: Divorced | S9: 2693 | T9: 13335 | U9: 1 | V9: Y | W9: No | X9: 22 | Y9: 4 | Z9: 2 | AA9: 80 | AB9: 1 | AC9: 1 | AD9: 2 | AE9: 3 | AF9: 1 | AG9: 0 | AH9: 0 | AI9: 0
A10: 38 | B10: No | C10: Travel_Frequently | D10: 216 | E10: Research & Development | F10: 23 | G10: 3 | H10: Life Sciences | I10: 1 | J10: 12 | K10: 4 | L10: Male | M10: 44 | N10: 2 | O10: 3 | P10: Manufacturing Director | Q10: 3 | R10: Single | S10: 9526 | T10: 8787 | U10: 0 | V10: Y | W10: No | X10: 21 | Y10: 4 | Z10: 2 | AA10: 80 | AB10: 0 | AC10: 10 | AD10: 2 | AE10: 3 | AF10: 9 | AG10: 7 | AH10: 1 | AI10: 8
A11: 36 | B11: No | C11: Travel_Rarely | D11: 1299 | E11: Research & Development | F11: 27 | G11: 3 | H11: Medical | I11: 1 | J11: 13 | K11: 3 | L11: Male | M11: 94 | N11: 3 | O11: 2 | P11: Healthcare Representative | Q11: 3 | R11: Married | S11: 5237 | T11: 16577 | U11: 6 | V11: Y | W11: No | X11: 13 | Y11: 3 | Z11: 2 | AA11: 80 | AB11: 2 | AC11: 17 | AD11: 3 | AE11: 2 | AF11: 7 | AG11: 7 | AH11: 7 | AI11: 7
A12: 35 | B12: No | C12: Travel_Rarely | D12: 809 | E12: Research & Development | F12: 16 | G12: 3 | H12: Medical | I12: 1 | J12: 14 | K12: 1 | L12: Male | M12: 84 | N12: 4 | O12: 1 | P12: Laboratory Technician | Q12: 2 | R12: Married | S12: 2426 | T12: 16479 | U12: 0 | V12: Y | W12: No | X12: 13 | Y12: 3 | Z12: 3 | AA12: 80 | AB12: 1 | AC12: 6 | AD12: 5 | AE12: 3 | AF12: 5 | AG12: 4 | AH12: 0 | AI12: 3
A13: 29 | B13: No | C13: Travel_Rarely | D13: 153 | E13: Research & Development | F13: 15 | G13: 2 | H13: Life Sciences | I13: 1 | J13: 15 | K13: 4 | L13: Female | M13: 49 | N13: 2 | O13: 2 | P13: Laboratory Technician | Q13: 3 | R13: Single | S13: 4193 | T13: 12682 | U13: 0 | V13: Y | W13: Yes | X13: 12 | Y13: 3 | Z13: 4 | AA13: 80 | AB13: 0 | AC13: 10 | AD13: 3 | AE13: 3 | AF13: 9 | AG13: 5 | AH13: 0 | AI13: 8
... A1471: 34 | B1471: No | C1471: Travel_Rarely | D1471: 628 | E1471: Research & Development | F1471: 8 | G1471: 3 | H1471: Medical | I1471: 1 | J1471: 2068 | K1471: 2 | L1471: Male | M1471: 82 | N1471: 4 | O1471: 2 | P1471: Laboratory Technician | Q1471: 3 | R1471: Married | S1471: 4404 | T1471: 10228 | U1471: 2 | V1471: Y | W1471: No | X1471: 12 | Y1471: 3 | Z1471: 1 | AA1471: 80 | AB1471: 0 | AC1471: 6 | AD1471: 3 | AE1471: 4 | AF1471: 4 | AG1471: 3 | AH1471: 1 | AI1471: 2

Sheet Project overview
B2: Project Title | C2: IBM HR Analytics Dashboard
C3: Employee Attrition, Burnout & Workforce Risk Analysis
B7: Project Objective | C7: This project analyzes IBM HR employee data to identify patterns related to attrition, burnout, compensation, promotion stagnation, and workforce risk. The dashboard was built in Microsoft Excel using advanced analytical and visualization techniques to support HR decision-making.
B11: Tools & Features Used
C12: • PivotTables & PivotCharts
C13: • Interactive slicers
C14: • XLOOKUP employee profile system
C15: • Conditional formatting & heatmaps
C16: • Risk scoring models
C17: • Burnout & attrition analysis
C18: • Excel tables and added analysis columns (risk flags, burnout score, salary bands)
C19: • Practice project on the public IBM HR Analytics dataset (1,470 fictional employees)
C20: • Dynamic KPI cards
C21: • Executive-style dashboard design
B23: Key Analytical Areas | C23: The dashboard focuses on: • Employee attrition risk • Burnout indicators • Promotion stagnation analysis • Compensation and salary insights • Workforce segmentation • Department-level HR trends
B26: Navigation Instructions | C26: Dashboard → main interactive analytics page KPI_Pivot, Attrition, Compensation&Pay and the other topic sheets → PivotTable analysis HR_Data → analysis dataset with the added columns KPIs_overview → headline KPIs Findings → written findings with the figures
B29: Key Insights | C29: Overtime: 30.5% attrition with overtime against 10.4% without
C30: Tenure: 34.9% attrition in the first two years, 8.1% after ten years
C31: Lower salary bands contain higher concentrations of attrition and risk
C32: Tested and not supported: time since last promotion (leavers 1.95 years, stayers 2.23) and department-level burnout do not explain attrition
B36: Prepared by: Kimia Mirkamali

Sheet Dashboard
C12: =KPI_Pivot!C5 -> 1470 | F12: =KPI_Pivot!N6 -> 0.16122449 | I12: =KPI_Pivot!G5 -> 314 | L12: =KPI_Pivot!J5 -> 0.38312925 | O12: =KPI_Pivot!Q5 -> 6502.9313 | R12: =KPI_Pivot!D11 -> 147 | U12: =KPI_Pivot!K11 -> 0.29482993 | X12: =KPI_Pivot!Q10 -> 260
C13: Total Employees | F13: Attrition Rate | I13: High Risk Employees | L13: Average Risk Score | O13: Average Monthly Income | U13: Burnout Score
R15: High Burnout Employees | X15: Employees with high Stagnation
F57: Department Risk Heatmap | K57: Average of MonthlyIncome | L57: Attrition | O57: Count of EmployeeNumber | P57: BurnoutLevel | T57: Count of EmployeeNumber | U57: StagnationLevel | Y57: Count of EmployeeNumber | Z57: SalaryBands
F58: Count of EmployeeCount | G58: AtriRiskCategory | K58: AtriRiskCategory | L58: No | M58: Yes | O58: Department | P58: High Burnout | Q58: Low Burnout | R58: Medium Burnout | T58: Department | U58: High Stagnation | V58: Low Stagnation | W58: Medium Stagnation | Y58: Department | Z58: High Salary | AA58: Low Salary | AB58: Medium Salary | AC58: Grand Total
F59: Department | G59: High Risk | H59: Low Risk | I59: Medium Risk | K59: High Risk | L59: 10504.576 | M59: 8388.8333 | O59: Human Resources | P59: 0.031746032 | Q59: 0.66666667 | R59: 0.3015873 | T59: Human Resources | U59: 8 | V59: 49 | W59: 6 | Y59: Human Resources | Z59: 16 | AA59: 32 | AB59: 15 | AC59: 63
F60: Human Resources | G60: 13 | H60: 13 | I60: 37 | K60: Low Risk | L60: 6878.0679 | M60: 5276 | O60: Research & Development | P60: 0.10613944 | Q60: 0.61186264 | R60: 0.28199792 | T60: Research & Development | U60: 160 | V60: 725 | W60: 76 | Y60: Research & Development | Z60: 230 | AA60: 431 | AB60: 300 | AC60: 961
F61: Research & Development | G61: 204 | H61: 253 | I61: 504 | K61: Medium Risk | L61: 5065.3612 | M61: 3886.1646 | O61: Sales | P61: 0.096412556 | Q61: 0.63004484 | R61: 0.2735426 | T61: Sales | U61: 92 | V61: 323 | W61: 31 | Y61: Sales | Z61: 135 | AA61: 79 | AB61: 232 | AC61: 446
F62: Sales | G62: 97 | H62: 139 | I62: 210 | K62: Grand Total | L62: 6832.7397 | M62: 4787.0928 | O62: Grand Total | P62: 0.1 | Q62: 0.61972789 | R62: 0.28027211 | Y62: Grand Total | Z62: 381 | AA62: 542 | AB62: 547 | AC62: 1470
G69: Employee Risk Profile
B70: Insight | G70: 1 | H70: Employee Number
B71: Key Burnout Insights: | G71: =_xlfn.XLOOKUP(G70,HR[EmployeeNumber],HR[Department]) -> Sales | H71: Department
B72: • Employees with overtime show higher burnout scores (overtime is one input of the score) | G72: =_xlfn.XLOOKUP(G70,HR[EmployeeNumber],HR[JobRole]) -> Sales Executive | H72: Job Role
B73: • Burnout score and attrition move together; the score is built from risk factors, so part of this is by design | G73: =_xlfn.XLOOKUP(G70,HR[EmployeeNumber],HR[MonthlyIncome]) -> 5993 | H73: Monthly Income
B74: • Burnout scores differ little between departments and do not explain why Sales and HR lose more people | G74: =_xlfn.XLOOKUP(G70,HR[EmployeeNumber],HR[AttritionRiskScore]) -> 0.7 | H74: Risk Score
G75: =_xlfn.XLOOKUP(G70,HR[EmployeeNumber],HR[AtriRiskCategory]) -> Medium Risk | H75: Risk Level
G76: =_xlfn.XLOOKUP(G70,HR[EmployeeNumber],HR[OverTime]) -> Yes | H76: OverTime
B77: Strategic HR Recommendations | G77: =_xlfn.XLOOKUP(G70,HR[EmployeeNumber],HR[JobSatisfaction]) -> 4 | H77: Job Satisfaction
B78: • Review overtime exposure: attrition is about three times higher with overtime in every department • Strengthen onboarding and early-tenure support (34.9% attrition in the first two years) • Review pay in the low salary band, where attrition is highest • Monitor employees with low job involvement, job satisfaction or work-life balance ratings | G78: =_xlfn.XLOOKUP(G70,HR[EmployeeNumber],HR[WorkLifeBalance]) -> 1 | H78: WorkLife Balance
G79: =_xlfn.XLOOKUP(G70,HR[EmployeeNumber],HR[YearsAtCompany]) -> 6 | H79: Years At Company
G80: =_xlfn.XLOOKUP(G70,HR[EmployeeNumber],HR[EnvironmentSatisfaction]) -> 2 | H80: Environmental Satisfaction
G81: =_xlfn.XLOOKUP(G70,HR[EmployeeNumber],HR[PerformanceRating]) -> 3 | H81: Performance Rating
G82: =_xlfn.XLOOKUP(G70,HR[EmployeeNumber],HR[TotalWorkingYears]) -> 8 | H82: Total Working Years
G83: =_xlfn.XLOOKUP(G70,HR[EmployeeNumber],HR[YearsInCurrentRole]) -> 4 | H83: Years in Current Role
G84: =_xlfn.XLOOKUP(G70,HR[EmployeeNumber],HR[YearsSinceLastPromotion]) -> 0 | H84: Years Since Last Promotion
C105: AtriRiskCategory
C106: High Risk | D106: Low Risk | E106: Medium Risk | F106: Grand Total
B107: Average of AttritionRiskScore | C107: 0.34936306 | D107: 0.17728395 | E107: 0.50825566 | F107: 0.38312925

Sheet KPI_Pivot
C4: Count of EmployeeNumber | F4: AtriRiskCategory | G4: Count of EmployeeNumber | J4: Average of AttritionRiskScore | M4: Attrition | N4: Count of EmployeeNumber | Q4: Average of MonthlyIncome
C5: 1470 | F5: High Risk | G5: 314 | J5: 0.38312925 | M5: No | N5: 0.83877551 | Q5: 6502.9313
F6: Low Risk | G6: 405 | M6: Yes | N6: 0.16122449
F7: Medium Risk | G7: 751 | M7: Grand Total | N7: 1
F8: Grand Total | G8: 1470
P9: StagnationLevel | Q9: Count of EmployeeNumber | S9: Count of EmployeeNumber | T9: Attrition
C10: BurnoutLevel | D10: Count of EmployeeNumber | F10: Count of EmployeeNumber | G10: Attrition | K10: Average of Burnout | M10: LowProFlag | N10: Count of EmployeeNumber | P10: High Stagnation | Q10: 260 | S10: StagnationLevel | T10: No | U10: Yes | V10: Grand Total
C11: High Burnout | D11: 147 | F11: BurnoutLevel | G11: No | H11: Yes | I11: Grand Total | K11: 0.29482993 | M11: 0 | N11: 1210 | P11: Low Stagnation | Q11: 1097 | S11: High Stagnation | T11: 0.85769231 | U11: 0.14230769 | V11: 1
C12: Low Burnout | D12: 911 | F12: High Burnout | G12: 0.068707483 | H12: 0.031292517 | I12: 0.1 | M12: 1 | N12: 260 | P12: Medium Stagnation | Q12: 113 | S12: Low Stagnation | T12: 0.83044667 | U12: 0.16955333 | V12: 1
C13: Medium Burnout | D13: 412 | F13: Low Burnout | G13: 0.56122449 | H13: 0.058503401 | I13: 0.61972789 | M13: Grand Total | N13: 1470 | P13: Grand Total | Q13: 1470 | S13: Medium Stagnation | T13: 0.87610619 | U13: 0.12389381 | V13: 1
C14: Grand Total | D14: 1470 | F14: Medium Burnout | G14: 0.20884354 | H14: 0.071428571 | I14: 0.28027211 | S14: Grand Total | T14: 0.83877551 | U14: 0.16122449 | V14: 1
F15: Grand Total | G15: 0.83877551 | H15: 0.16122449 | I15: 1
C17: Count of EmployeeNumber | D17: BurnoutLevel
C18: StagnationLevel | D18: High Burnout | E18: Low Burnout | F18: Medium Burnout | G18: Grand Total | J18: Count of EmployeeNumber | K18: Attrition | O18: SalaryBands | P18: Average of AttritionRiskScore | R18: JobRole | S18: Average of MonthlyIncome
C19: High Stagnation | D19: 0.15769231 | E19: 0.52692308 | F19: 0.31538462 | G19: 1 | J19: SalaryBands | K19: No | L19: Yes | M19: Grand Total | O19: High Salary | P19: 0.29396325 | R19: Healthcare Representative | S19: 7528.7634
C20: Low Stagnation | D20: 0.084776664 | E20: 0.63719234 | F20: 0.27803099 | G20: 1 | J20: High Salary | K20: 341 | L20: 40 | M20: 381 | O20: Low Salary | P20: 0.43238007 | R20: Human Resources | S20: 4235.75
C21: Medium Stagnation | D21: 0.11504425 | E21: 0.66371681 | F21: 0.22123894 | G21: 1 | J21: Low Salary | K21: 405 | L21: 137 | M21: 542 | O21: Medium Salary | P21: 0.3964351 | R21: Laboratory Technician | S21: 3237.1699
C22: Grand Total | D22: 0.1 | E22: 0.61972789 | F22: 0.28027211 | G22: 1 | J22: Medium Salary | K22: 487 | L22: 60 | M22: 547 | O22: Grand Total | P22: 0.38312925 | R22: Manager | S22: 17181.676
J23: Grand Total | K23: 1233 | L23: 237 | M23: 1470 | R23: Manufacturing Director | S23: 7295.1379
R24: Research Director | S24: 16033.55
R25: Research Scientist | S25: 3239.9726
R26: Sales Executive | S26: 6924.2791
R27: Sales Representative | S27: 2626
R28: Grand Total | S28: 6502.9313

Sheet HR
A1: Age | B1: Attrition | C1: BusinessTravel | D1: DailyRate | E1: Department | F1: DistanceFromHome | G1: Education | H1: EducationField | I1: EmployeeCount | J1: EmployeeNumber | K1: EnvironmentSatisfaction | L1: Gender | M1: HourlyRate | N1: JobInvolvement | O1: JobLevel | P1: JobRole | Q1: JobSatisfaction | R1: MaritalStatus | S1: MonthlyIncome | T1: MonthlyRate | U1: NumCompaniesWorked | V1: Over18 | W1: OverTime | X1: PercentSalaryHike | Y1: PerformanceRating | Z1: RelationshipSatisfaction | AA1: StandardHours | AB1: StockOptionLevel | AC1: TotalWorkingYears | AD1: TrainingTimesLastYear | AE1: WorkLifeBalance | AF1: YearsAtCompany | AG1: YearsInCurrentRole | AH1: YearsSinceLastPromotion | AI1: YearsWithCurrManager | AJ1: OverTimeFlag | AK1: LowJobSatisFlag | AL1: LowWLBFlag | AM1: LowSalaryFlag | AN1: LowEnviFlag | AO1: LowProFlag | AP1: AttritionRiskScore | AQ1: AtriRiskCategory | AR1: Burnout | AS1: BurnoutLevel | AT1: StagnationLevel | AU1: SalaryBands | AV1: Column13 | AW1: Column14 | AX1: Column15 | AY1: Column16 | AZ1: Column17 | BA1: Column18 | BB1: Column19 | BC1: Column20 | BD1: Column21 | BE1: Column22 | BF1: Column23 | BG1: Column24 | BH1: Column25 | BI1: Column26 | BJ1: Column27 | BK1: Column28 | BL1: Column29 | BM1: Column30 | BN1: Column31 | BO1: Column32 | BP1: Column33 | BQ1: Column34 | BR1: Column35 | BS1: Column36 | BT1: Column37 | BU1: Column38 | BV1: Column39 | BW1: Column40 | BX1: Column41 | BY1: Column42 | BZ1: Column43 | CA1: Column44 | CB1: Column45 | CC1: Column46 | CD1: Column47 | CE1: Column48 | CF1: Column49 | CG1: Column50 | CH1: Column51 | CI1: Column52 | CJ1: Column53 | CK1: Column54 | CL1: Column55 | CM1: Column56 | CN1: Column57 | CO1: Column58 | CP1: Column59 | CQ1: Column60 | CR1: Column61 | CS1: Column62 | CT1: Column63 | CU1: Column64 | CV1: Column65
A2: 41 | B2: Yes | C2: Travel_Rarely | D2: 1102 | E2: Sales | F2: 1 | G2: 2 | H2: Life Sciences | I2: 1 | J2: 1 | K2: 2 | L2: Female | M2: 94 | N2: 3 | O2: 2 | P2: Sales Executive | Q2: 4 | R2: Single | S2: 5993 | T2: 19479 | U2: 8 | V2: Y | W2: Yes | X2: 11 | Y2: 3 | Z2: 1 | AA2: 80 | AB2: 0 | AC2: 8 | AD2: 0 | AE2: 1 | AF2: 6 | AG2: 4 | AH2: 0 | AI2: 5 | AJ2: =IF(HR[[#This Row],[OverTime]]="Yes",1,0) -> 1 | AK2: =IF(HR[[#This Row],[JobSatisfaction]]<=2,1,0) -> 0 | AL2: =IF(HR[[#This Row],[WorkLifeBalance]]<=2,1,0) -> 1 | AM2: =IF(HR[[#This Row],[MonthlyIncome]]<AVERAGE(HR[MonthlyIncome]),1,0) -> 1 | AN2: =IF(HR[[#This Row],[EnvironmentSatisfaction]]<=2,1,0) -> 1 | AO2: =IF(HR[[#This Row],[YearsSinceLastPromotion]]>4,1,0) -> 0 | AP2: =(HR[[#This Row],[OverTimeFlag]]*1.5+HR[[#This Row],[LowJobSatisFlag]]*2.5+HR[[#This Row],[LowWLBFlag]]*2+HR[[#This Row],[LowSalaryFlag]]*1.5+HR[[#This Row],[LowEnviFlag]]*2+HR[[#This Row],[LowProFlag]]*0.5)/10 -> 0.7 | AQ2: =IF(A2>=_xlfn.PERCENTILE.INC($A$2:$A$1000,0.8),"High Risk", IF(HR[[#This Row],[AttritionRiskScore]]>=_xlfn.PERCENTILE.INC($AP$2:$AP$1000,0.5),"Medium Risk","Low Risk")) -> Medium Risk | AR2: =(HR[[#This Row],[OverTimeFlag]]*4+HR[[#This Row],[LowWLBFlag]]*3+HR[[#This Row],[LowJobSatisFlag]]*2+HR[[#This Row],[LowProFlag]]*1)/10 -> 0.7 | AS2: =IF(AR2>=0.7,"High Burnout",IF(AR2>=0.4,"Medium Burnout","Low Burnout")) -> High Burnout | AT2: =IF(HR[[#This Row],[YearsSinceLastPromotion]]>4,"High Stagnation", IF(HR[[#This Row],[YearsSinceLastPromotion]]>=3,"Medium Stagnation","Low Stagnation")) -> Low Stagnation | AU2: =IF(HR[[#This Row],[MonthlyIncome]]<4000,"Low Salary", IF(HR[[#This Row],[MonthlyIncome]]<8000,"Medium Salary","High Salary")) -> Medium Salary
A3: 49 | B3: No | C3: Travel_Frequently | D3: 279 | E3: Research & Development | F3: 8 | G3: 1 | H3: Life Sciences | I3: 1 | J3: 2 | K3: 3 | L3: Male | M3: 61 | N3: 2 | O3: 2 | P3: Research Scientist | Q3: 2 | R3: Married | S3: 5130 | T3: 24907 | U3: 1 | V3: Y | W3: No | X3: 23 | Y3: 4 | Z3: 4 | AA3: 80 | AB3: 1 | AC3: 10 | AD3: 3 | AE3: 3 | AF3: 10 | AG3: 7 | AH3: 1 | AI3: 7 | AJ3: =IF(HR[[#This Row],[OverTime]]="Yes",1,0) -> 0 | AK3: =IF(HR[[#This Row],[JobSatisfaction]]<=2,1,0) -> 1 | AL3: =IF(HR[[#This Row],[WorkLifeBalance]]<=2,1,0) -> 0 | AM3: =IF(HR[[#This Row],[MonthlyIncome]]<AVERAGE(HR[MonthlyIncome]),1,0) -> 1 | AN3: =IF(HR[[#This Row],[EnvironmentSatisfaction]]<=2,1,0) -> 0 | AO3: =IF(HR[[#This Row],[YearsSinceLastPromotion]]>4,1,0) -> 0 | AP3: =(HR[[#This Row],[OverTimeFlag]]*1.5+HR[[#This Row],[LowJobSatisFlag]]*2.5+HR[[#This Row],[LowWLBFlag]]*2+HR[[#This Row],[LowSalaryFlag]]*1.5+HR[[#This Row],[LowEnviFlag]]*2+HR[[#This Row],[LowProFlag]]*0.5)/10 -> 0.4 | AQ3: =IF(A3>=_xlfn.PERCENTILE.INC($A$2:$A$1000,0.8),"High Risk", IF(HR[[#This Row],[AttritionRiskScore]]>=_xlfn.PERCENTILE.INC($AP$2:$AP$1000,0.5),"Medium Risk","Low Risk")) -> High Risk | AR3: =(HR[[#This Row],[OverTimeFlag]]*4+HR[[#This Row],[LowWLBFlag]]*3+HR[[#This Row],[LowJobSatisFlag]]*2+HR[[#This Row],[LowProFlag]]*1)/10 -> 0.2 | AS3: =IF(AR3>=0.7,"High Burnout",IF(AR3>=0.4,"Medium Burnout","Low Burnout")) -> Low Burnout | AT3: =IF(HR[[#This Row],[YearsSinceLastPromotion]]>4,"High Stagnation", IF(HR[[#This Row],[YearsSinceLastPromotion]]>=3,"Medium Stagnation","Low Stagnation")) -> Low Stagnation | AU3: =IF(HR[[#This Row],[MonthlyIncome]]<4000,"Low Salary", IF(HR[[#This Row],[MonthlyIncome]]<8000,"Medium Salary","High Salary")) -> Medium Salary
A4: 37 | B4: Yes | C4: Travel_Rarely | D4: 1373 | E4: Research & Development | F4: 2 | G4: 2 | H4: Other | I4: 1 | J4: 4 | K4: 4 | L4: Male | M4: 92 | N4: 2 | O4: 1 | P4: Laboratory Technician | Q4: 3 | R4: Single | S4: 2090 | T4: 2396 | U4: 6 | V4: Y | W4: Yes | X4: 15 | Y4: 3 | Z4: 2 | AA4: 80 | AB4: 0 | AC4: 7 | AD4: 3 | AE4: 3 | AF4: 0 | AG4: 0 | AH4: 0 | AI4: 0 | AJ4: =IF(HR[[#This Row],[OverTime]]="Yes",1,0) -> 1 | AK4: =IF(HR[[#This Row],[JobSatisfaction]]<=2,1,0) -> 0 | AL4: =IF(HR[[#This Row],[WorkLifeBalance]]<=2,1,0) -> 0 | AM4: =IF(HR[[#This Row],[MonthlyIncome]]<AVERAGE(HR[MonthlyIncome]),1,0) -> 1 | AN4: =IF(HR[[#This Row],[EnvironmentSatisfaction]]<=2,1,0) -> 0 | AO4: =IF(HR[[#This Row],[YearsSinceLastPromotion]]>4,1,0) -> 0 | AP4: =(HR[[#This Row],[OverTimeFlag]]*1.5+HR[[#This Row],[LowJobSatisFlag]]*2.5+HR[[#This Row],[LowWLBFlag]]*2+HR[[#This Row],[LowSalaryFlag]]*1.5+HR[[#This Row],[LowEnviFlag]]*2+HR[[#This Row],[LowProFlag]]*0.5)/10 -> 0.3 | AQ4: =IF(A4>=_xlfn.PERCENTILE.INC($A$2:$A$1000,0.8),"High Risk", IF(HR[[#This Row],[AttritionRiskScore]]>=_xlfn.PERCENTILE.INC($AP$2:$AP$1000,0.5),"Medium Risk","Low Risk")) -> Low Risk | AR4: =(HR[[#This Row],[OverTimeFlag]]*4+HR[[#This Row],[LowWLBFlag]]*3+HR[[#This Row],[LowJobSatisFlag]]*2+HR[[#This Row],[LowProFlag]]*1)/10 -> 0.4 | AS4: =IF(AR4>=0.7,"High Burnout",IF(AR4>=0.4,"Medium Burnout","Low Burnout")) -> Medium Burnout | AT4: =IF(HR[[#This Row],[YearsSinceLastPromotion]]>4,"High Stagnation", IF(HR[[#This Row],[YearsSinceLastPromotion]]>=3,"Medium Stagnation","Low Stagnation")) -> Low Stagnation | AU4: =IF(HR[[#This Row],[MonthlyIncome]]<4000,"Low Salary", IF(HR[[#This Row],[MonthlyIncome]]<8000,"Medium Salary","High Salary")) -> Low Salary
A5: 33 | B5: No | C5: Travel_Frequently | D5: 1392 | E5: Research & Development | F5: 3 | G5: 4 | H5: Life Sciences | I5: 1 | J5: 5 | K5: 4 | L5: Female | M5: 56 | N5: 3 | O5: 1 | P5: Research Scientist | Q5: 3 | R5: Married | S5: 2909 | T5: 23159 | U5: 1 | V5: Y | W5: Yes | X5: 11 | Y5: 3 | Z5: 3 | AA5: 80 | AB5: 0 | AC5: 8 | AD5: 3 | AE5: 3 | AF5: 8 | AG5: 7 | AH5: 3 | AI5: 0 | AJ5: =IF(HR[[#This Row],[OverTime]]="Yes",1,0) -> 1 | AK5: =IF(HR[[#This Row],[JobSatisfaction]]<=2,1,0) -> 0 | AL5: =IF(HR[[#This Row],[WorkLifeBalance]]<=2,1,0) -> 0 | AM5: =IF(HR[[#This Row],[MonthlyIncome]]<AVERAGE(HR[MonthlyIncome]),1,0) -> 1 | AN5: =IF(HR[[#This Row],[EnvironmentSatisfaction]]<=2,1,0) -> 0 | AO5: =IF(HR[[#This Row],[YearsSinceLastPromotion]]>4,1,0) -> 0 | AP5: =(HR[[#This Row],[OverTimeFlag]]*1.5+HR[[#This Row],[LowJobSatisFlag]]*2.5+HR[[#This Row],[LowWLBFlag]]*2+HR[[#This Row],[LowSalaryFlag]]*1.5+HR[[#This Row],[LowEnviFlag]]*2+HR[[#This Row],[LowProFlag]]*0.5)/10 -> 0.3 | AQ5: =IF(A5>=_xlfn.PERCENTILE.INC($A$2:$A$1000,0.8),"High Risk", IF(HR[[#This Row],[AttritionRiskScore]]>=_xlfn.PERCENTILE.INC($AP$2:$AP$1000,0.5),"Medium Risk","Low Risk")) -> Low Risk | AR5: =(HR[[#This Row],[OverTimeFlag]]*4+HR[[#This Row],[LowWLBFlag]]*3+HR[[#This Row],[LowJobSatisFlag]]*2+HR[[#This Row],[LowProFlag]]*1)/10 -> 0.4 | AS5: =IF(AR5>=0.7,"High Burnout",IF(AR5>=0.4,"Medium Burnout","Low Burnout")) -> Medium Burnout | AT5: =IF(HR[[#This Row],[YearsSinceLastPromotion]]>4,"High Stagnation", IF(HR[[#This Row],[YearsSinceLastPromotion]]>=3,"Medium Stagnation","Low Stagnation")) -> Medium Stagnation | AU5: =IF(HR[[#This Row],[MonthlyIncome]]<4000,"Low Salary", IF(HR[[#This Row],[MonthlyIncome]]<8000,"Medium Salary","High Salary")) -> Low Salary
A6: 27 | B6: No | C6: Travel_Rarely | D6: 591 | E6: Research & Development | F6: 2 | G6: 1 | H6: Medical | I6: 1 | J6: 7 | K6: 1 | L6: Male | M6: 40 | N6: 3 | O6: 1 | P6: Laboratory Technician | Q6: 2 | R6: Married | S6: 3468 | T6: 16632 | U6: 9 | V6: Y | W6: No | X6: 12 | Y6: 3 | Z6: 4 | AA6: 80 | AB6: 1 | AC6: 6 | AD6: 3 | AE6: 3 | AF6: 2 | AG6: 2 | AH6: 2 | AI6: 2 | AJ6: =IF(HR[[#This Row],[OverTime]]="Yes",1,0) -> 0 | AK6: =IF(HR[[#This Row],[JobSatisfaction]]<=2,1,0) -> 1 | AL6: =IF(HR[[#This Row],[WorkLifeBalance]]<=2,1,0) -> 0 | AM6: =IF(HR[[#This Row],[MonthlyIncome]]<AVERAGE(HR[MonthlyIncome]),1,0) -> 1 | AN6: =IF(HR[[#This Row],[EnvironmentSatisfaction]]<=2,1,0) -> 1 | AO6: =IF(HR[[#This Row],[YearsSinceLastPromotion]]>4,1,0) -> 0 | AP6: =(HR[[#This Row],[OverTimeFlag]]*1.5+HR[[#This Row],[LowJobSatisFlag]]*2.5+HR[[#This Row],[LowWLBFlag]]*2+HR[[#This Row],[LowSalaryFlag]]*1.5+HR[[#This Row],[LowEnviFlag]]*2+HR[[#This Row],[LowProFlag]]*0.5)/10 -> 0.6 | AQ6: =IF(A6>=_xlfn.PERCENTILE.INC($A$2:$A$1000,0.8),"High Risk", IF(HR[[#This Row],[AttritionRiskScore]]>=_xlfn.PERCENTILE.INC($AP$2:$AP$1000,0.5),"Medium Risk","Low Risk")) -> Medium Risk | AR6: =(HR[[#This Row],[OverTimeFlag]]*4+HR[[#This Row],[LowWLBFlag]]*3+HR[[#This Row],[LowJobSatisFlag]]*2+HR[[#This Row],[LowProFlag]]*1)/10 -> 0.2 | AS6: =IF(AR6>=0.7,"High Burnout",IF(AR6>=0.4,"Medium Burnout","Low Burnout")) -> Low Burnout | AT6: =IF(HR[[#This Row],[YearsSinceLastPromotion]]>4,"High Stagnation", IF(HR[[#This Row],[YearsSinceLastPromotion]]>=3,"Medium Stagnation","Low Stagnation")) -> Low Stagnation | AU6: =IF(HR[[#This Row],[MonthlyIncome]]<4000,"Low Salary", IF(HR[[#This Row],[MonthlyIncome]]<8000,"Medium Salary","High Salary")) -> Low Salary
A7: 32 | B7: No | C7: Travel_Frequently | D7: 1005 | E7: Research & Development | F7: 2 | G7: 2 | H7: Life Sciences | I7: 1 | J7: 8 | K7: 4 | L7: Male | M7: 79 | N7: 3 | O7: 1 | P7: Laboratory Technician | Q7: 4 | R7: Single | S7: 3068 | T7: 11864 | U7: 0 | V7: Y | W7: No | X7: 13 | Y7: 3 | Z7: 3 | AA7: 80 | AB7: 0 | AC7: 8 | AD7: 2 | AE7: 2 | AF7: 7 | AG7: 7 | AH7: 3 | AI7: 6 | AJ7: =IF(HR[[#This Row],[OverTime]]="Yes",1,0) -> 0 | AK7: =IF(HR[[#This Row],[JobSatisfaction]]<=2,1,0) -> 0 | AL7: =IF(HR[[#This Row],[WorkLifeBalance]]<=2,1,0) -> 1 | AM7: =IF(HR[[#This Row],[MonthlyIncome]]<AVERAGE(HR[MonthlyIncome]),1,0) -> 1 | AN7: =IF(HR[[#This Row],[EnvironmentSatisfaction]]<=2,1,0) -> 0 | AO7: =IF(HR[[#This Row],[YearsSinceLastPromotion]]>4,1,0) -> 0 | AP7: =(HR[[#This Row],[OverTimeFlag]]*1.5+HR[[#This Row],[LowJobSatisFlag]]*2.5+HR[[#This Row],[LowWLBFlag]]*2+HR[[#This Row],[LowSalaryFlag]]*1.5+HR[[#This Row],[LowEnviFlag]]*2+HR[[#This Row],[LowProFlag]]*0.5)/10 -> 0.35 | AQ7: =IF(A7>=_xlfn.PERCENTILE.INC($A$2:$A$1000,0.8),"High Risk", IF(HR[[#This Row],[AttritionRiskScore]]>=_xlfn.PERCENTILE.INC($AP$2:$AP$1000,0.5),"Medium Risk","Low Risk")) -> Medium Risk | AR7: =(HR[[#This Row],[OverTimeFlag]]*4+HR[[#This Row],[LowWLBFlag]]*3+HR[[#This Row],[LowJobSatisFlag]]*2+HR[[#This Row],[LowProFlag]]*1)/10 -> 0.3 | AS7: =IF(AR7>=0.7,"High Burnout",IF(AR7>=0.4,"Medium Burnout","Low Burnout")) -> Low Burnout | AT7: =IF(HR[[#This Row],[YearsSinceLastPromotion]]>4,"High Stagnation", IF(HR[[#This Row],[YearsSinceLastPromotion]]>=3,"Medium Stagnation","Low Stagnation")) -> Medium Stagnation | AU7: =IF(HR[[#This Row],[MonthlyIncome]]<4000,"Low Salary", IF(HR[[#This Row],[MonthlyIncome]]<8000,"Medium Salary","High Salary")) -> Low Salary
A8: 59 | B8: No | C8: Travel_Rarely | D8: 1324 | E8: Research & Development | F8: 3 | G8: 3 | H8: Medical | I8: 1 | J8: 10 | K8: 3 | L8: Female | M8: 81 | N8: 4 | O8: 1 | P8: Laboratory Technician | Q8: 1 | R8: Married | S8: 2670 | T8: 9964 | U8: 4 | V8: Y | W8: Yes | X8: 20 | Y8: 4 | Z8: 1 | AA8: 80 | AB8: 3 | AC8: 12 | AD8: 3 | AE8: 2 | AF8: 1 | AG8: 0 | AH8: 0 | AI8: 0 | AJ8: =IF(HR[[#This Row],[OverTime]]="Yes",1,0) -> 1 | AK8: =IF(HR[[#This Row],[JobSatisfaction]]<=2,1,0) -> 1 | AL8: =IF(HR[[#This Row],[WorkLifeBalance]]<=2,1,0) -> 1 | AM8: =IF(HR[[#This Row],[MonthlyIncome]]<AVERAGE(HR[MonthlyIncome]),1,0) -> 1 | AN8: =IF(HR[[#This Row],[EnvironmentSatisfaction]]<=2,1,0) -> 0 | AO8: =IF(HR[[#This Row],[YearsSinceLastPromotion]]>4,1,0) -> 0 | AP8: =(HR[[#This Row],[OverTimeFlag]]*1.5+HR[[#This Row],[LowJobSatisFlag]]*2.5+HR[[#This Row],[LowWLBFlag]]*2+HR[[#This Row],[LowSalaryFlag]]*1.5+HR[[#This Row],[LowEnviFlag]]*2+HR[[#This Row],[LowProFlag]]*0.5)/10 -> 0.75 | AQ8: =IF(A8>=_xlfn.PERCENTILE.INC($A$2:$A$1000,0.8),"High Risk", IF(HR[[#This Row],[AttritionRiskScore]]>=_xlfn.PERCENTILE.INC($AP$2:$AP$1000,0.5),"Medium Risk","Low Risk")) -> High Risk | AR8: =(HR[[#This Row],[OverTimeFlag]]*4+HR[[#This Row],[LowWLBFlag]]*3+HR[[#This Row],[LowJobSatisFlag]]*2+HR[[#This Row],[LowProFlag]]*1)/10 -> 0.9 | AS8: =IF(AR8>=0.7,"High Burnout",IF(AR8>=0.4,"Medium Burnout","Low Burnout")) -> High Burnout | AT8: =IF(HR[[#This Row],[YearsSinceLastPromotion]]>4,"High Stagnation", IF(HR[[#This Row],[YearsSinceLastPromotion]]>=3,"Medium Stagnation","Low Stagnation")) -> Low Stagnation | AU8: =IF(HR[[#This Row],[MonthlyIncome]]<4000,"Low Salary", IF(HR[[#This Row],[MonthlyIncome]]<8000,"Medium Salary","High Salary")) -> Low Salary
A9: 30 | B9: No | C9: Travel_Rarely | D9: 1358 | E9: Research & Development | F9: 24 | G9: 1 | H9: Life Sciences | I9: 1 | J9: 11 | K9: 4 | L9: Male | M9: 67 | N9: 3 | O9: 1 | P9: Laboratory Technician | Q9: 3 | R9: Divorced | S9: 2693 | T9: 13335 | U9: 1 | V9: Y | W9: No | X9: 22 | Y9: 4 | Z9: 2 | AA9: 80 | AB9: 1 | AC9: 1 | AD9: 2 | AE9: 3 | AF9: 1 | AG9: 0 | AH9: 0 | AI9: 0 | AJ9: =IF(HR[[#This Row],[OverTime]]="Yes",1,0) -> 0 | AK9: =IF(HR[[#This Row],[JobSatisfaction]]<=2,1,0) -> 0 | AL9: =IF(HR[[#This Row],[WorkLifeBalance]]<=2,1,0) -> 0 | AM9: =IF(HR[[#This Row],[MonthlyIncome]]<AVERAGE(HR[MonthlyIncome]),1,0) -> 1 | AN9: =IF(HR[[#This Row],[EnvironmentSatisfaction]]<=2,1,0) -> 0 | AO9: =IF(HR[[#This Row],[YearsSinceLastPromotion]]>4,1,0) -> 0 | AP9: =(HR[[#This Row],[OverTimeFlag]]*1.5+HR[[#This Row],[LowJobSatisFlag]]*2.5+HR[[#This Row],[LowWLBFlag]]*2+HR[[#This Row],[LowSalaryFlag]]*1.5+HR[[#This Row],[LowEnviFlag]]*2+HR[[#This Row],[LowProFlag]]*0.5)/10 -> 0.15 | AQ9: =IF(A9>=_xlfn.PERCENTILE.INC($A$2:$A$1000,0.8),"High Risk", IF(HR[[#This Row],[AttritionRiskScore]]>=_xlfn.PERCENTILE.INC($AP$2:$AP$1000,0.5),"Medium Risk","Low Risk")) -> Low Risk | AR9: =(HR[[#This Row],[OverTimeFlag]]*4+HR[[#This Row],[LowWLBFlag]]*3+HR[[#This Row],[LowJobSatisFlag]]*2+HR[[#This Row],[LowProFlag]]*1)/10 -> 0 | AS9: =IF(AR9>=0.7,"High Burnout",IF(AR9>=0.4,"Medium Burnout","Low Burnout")) -> Low Burnout | AT9: =IF(HR[[#This Row],[YearsSinceLastPromotion]]>4,"High Stagnation", IF(HR[[#This Row],[YearsSinceLastPromotion]]>=3,"Medium Stagnation","Low Stagnation")) -> Low Stagnation | AU9: =IF(HR[[#This Row],[MonthlyIncome]]<4000,"Low Salary", IF(HR[[#This Row],[MonthlyIncome]]<8000,"Medium Salary","High Salary")) -> Low Salary
A10: 38 | B10: No | C10: Travel_Frequently | D10: 216 | E10: Research & Development | F10: 23 | G10: 3 | H10: Life Sciences | I10: 1 | J10: 12 | K10: 4 | L10: Male | M10: 44 | N10: 2 | O10: 3 | P10: Manufacturing Director | Q10: 3 | R10: Single | S10: 9526 | T10: 8787 | U10: 0 | V10: Y | W10: No | X10: 21 | Y10: 4 | Z10: 2 | AA10: 80 | AB10: 0 | AC10: 10 | AD10: 2 | AE10: 3 | AF10: 9 | AG10: 7 | AH10: 1 | AI10: 8 | AJ10: =IF(HR[[#This Row],[OverTime]]="Yes",1,0) -> 0 | AK10: =IF(HR[[#This Row],[JobSatisfaction]]<=2,1,0) -> 0 | AL10: =IF(HR[[#This Row],[WorkLifeBalance]]<=2,1,0) -> 0 | AM10: =IF(HR[[#This Row],[MonthlyIncome]]<AVERAGE(HR[MonthlyIncome]),1,0) -> 0 | AN10: =IF(HR[[#This Row],[EnvironmentSatisfaction]]<=2,1,0) -> 0 | AO10: =IF(HR[[#This Row],[YearsSinceLastPromotion]]>4,1,0) -> 0 | AP10: =(HR[[#This Row],[OverTimeFlag]]*1.5+HR[[#This Row],[LowJobSatisFlag]]*2.5+HR[[#This Row],[LowWLBFlag]]*2+HR[[#This Row],[LowSalaryFlag]]*1.5+HR[[#This Row],[LowEnviFlag]]*2+HR[[#This Row],[LowProFlag]]*0.5)/10 -> 0 | AQ10: =IF(A10>=_xlfn.PERCENTILE.INC($A$2:$A$1000,0.8),"High Risk", IF(HR[[#This Row],[AttritionRiskScore]]>=_xlfn.PERCENTILE.INC($AP$2:$AP$1000,0.5),"Medium Risk","Low Risk")) -> Low Risk | AR10: =(HR[[#This Row],[OverTimeFlag]]*4+HR[[#This Row],[LowWLBFlag]]*3+HR[[#This Row],[LowJobSatisFlag]]*2+HR[[#This Row],[LowProFlag]]*1)/10 -> 0 | AS10: =IF(AR10>=0.7,"High Burnout",IF(AR10>=0.4,"Medium Burnout","Low Burnout")) -> Low Burnout | AT10: =IF(HR[[#This Row],[YearsSinceLastPromotion]]>4,"High Stagnation", IF(HR[[#This Row],[YearsSinceLastPromotion]]>=3,"Medium Stagnation","Low Stagnation")) -> Low Stagnation | AU10: =IF(HR[[#This Row],[MonthlyIncome]]<4000,"Low Salary", IF(HR[[#This Row],[MonthlyIncome]]<8000,"Medium Salary","High Salary")) -> High Salary
A11: 36 | B11: No | C11: Travel_Rarely | D11: 1299 | E11: Research & Development | F11: 27 | G11: 3 | H11: Medical | I11: 1 | J11: 13 | K11: 3 | L11: Male | M11: 94 | N11: 3 | O11: 2 | P11: Healthcare Representative | Q11: 3 | R11: Married | S11: 5237 | T11: 16577 | U11: 6 | V11: Y | W11: No | X11: 13 | Y11: 3 | Z11: 2 | AA11: 80 | AB11: 2 | AC11: 17 | AD11: 3 | AE11: 2 | AF11: 7 | AG11: 7 | AH11: 7 | AI11: 7 | AJ11: =IF(HR[[#This Row],[OverTime]]="Yes",1,0) -> 0 | AK11: =IF(HR[[#This Row],[JobSatisfaction]]<=2,1,0) -> 0 | AL11: =IF(HR[[#This Row],[WorkLifeBalance]]<=2,1,0) -> 1 | AM11: =IF(HR[[#This Row],[MonthlyIncome]]<AVERAGE(HR[MonthlyIncome]),1,0) -> 1 | AN11: =IF(HR[[#This Row],[EnvironmentSatisfaction]]<=2,1,0) -> 0 | AO11: =IF(HR[[#This Row],[YearsSinceLastPromotion]]>4,1,0) -> 1 | AP11: =(HR[[#This Row],[OverTimeFlag]]*1.5+HR[[#This Row],[LowJobSatisFlag]]*2.5+HR[[#This Row],[LowWLBFlag]]*2+HR[[#This Row],[LowSalaryFlag]]*1.5+HR[[#This Row],[LowEnviFlag]]*2+HR[[#This Row],[LowProFlag]]*0.5)/10 -> 0.4 | AQ11: =IF(A11>=_xlfn.PERCENTILE.INC($A$2:$A$1000,0.8),"High Risk", IF(HR[[#This Row],[AttritionRiskScore]]>=_xlfn.PERCENTILE.INC($AP$2:$AP$1000,0.5),"Medium Risk","Low Risk")) -> Medium Risk | AR11: =(HR[[#This Row],[OverTimeFlag]]*4+HR[[#This Row],[LowWLBFlag]]*3+HR[[#This Row],[LowJobSatisFlag]]*2+HR[[#This Row],[LowProFlag]]*1)/10 -> 0.4 | AS11: =IF(AR11>=0.7,"High Burnout",IF(AR11>=0.4,"Medium Burnout","Low Burnout")) -> Medium Burnout | AT11: =IF(HR[[#This Row],[YearsSinceLastPromotion]]>4,"High Stagnation", IF(HR[[#This Row],[YearsSinceLastPromotion]]>=3,"Medium Stagnation","Low Stagnation")) -> High Stagnation | AU11: =IF(HR[[#This Row],[MonthlyIncome]]<4000,"Low Salary", IF(HR[[#This Row],[MonthlyIncome]]<8000,"Medium Salary","High Salary")) -> Medium Salary
A12: 35 | B12: No | C12: Travel_Rarely | D12: 809 | E12: Research & Development | F12: 16 | G12: 3 | H12: Medical | I12: 1 | J12: 14 | K12: 1 | L12: Male | M12: 84 | N12: 4 | O12: 1 | P12: Laboratory Technician | Q12: 2 | R12: Married | S12: 2426 | T12: 16479 | U12: 0 | V12: Y | W12: No | X12: 13 | Y12: 3 | Z12: 3 | AA12: 80 | AB12: 1 | AC12: 6 | AD12: 5 | AE12: 3 | AF12: 5 | AG12: 4 | AH12: 0 | AI12: 3 | AJ12: =IF(HR[[#This Row],[OverTime]]="Yes",1,0) -> 0 | AK12: =IF(HR[[#This Row],[JobSatisfaction]]<=2,1,0) -> 1 | AL12: =IF(HR[[#This Row],[WorkLifeBalance]]<=2,1,0) -> 0 | AM12: =IF(HR[[#This Row],[MonthlyIncome]]<AVERAGE(HR[MonthlyIncome]),1,0) -> 1 | AN12: =IF(HR[[#This Row],[EnvironmentSatisfaction]]<=2,1,0) -> 1 | AO12: =IF(HR[[#This Row],[YearsSinceLastPromotion]]>4,1,0) -> 0 | AP12: =(HR[[#This Row],[OverTimeFlag]]*1.5+HR[[#This Row],[LowJobSatisFlag]]*2.5+HR[[#This Row],[LowWLBFlag]]*2+HR[[#This Row],[LowSalaryFlag]]*1.5+HR[[#This Row],[LowEnviFlag]]*2+HR[[#This Row],[LowProFlag]]*0.5)/10 -> 0.6 | AQ12: =IF(A12>=_xlfn.PERCENTILE.INC($A$2:$A$1000,0.8),"High Risk", IF(HR[[#This Row],[AttritionRiskScore]]>=_xlfn.PERCENTILE.INC($AP$2:$AP$1000,0.5),"Medium Risk","Low Risk")) -> Medium Risk | AR12: =(HR[[#This Row],[OverTimeFlag]]*4+HR[[#This Row],[LowWLBFlag]]*3+HR[[#This Row],[LowJobSatisFlag]]*2+HR[[#This Row],[LowProFlag]]*1)/10 -> 0.2 | AS12: =IF(AR12>=0.7,"High Burnout",IF(AR12>=0.4,"Medium Burnout","Low Burnout")) -> Low Burnout | AT12: =IF(HR[[#This Row],[YearsSinceLastPromotion]]>4,"High Stagnation", IF(HR[[#This Row],[YearsSinceLastPromotion]]>=3,"Medium Stagnation","Low Stagnation")) -> Low Stagnation | AU12: =IF(HR[[#This Row],[MonthlyIncome]]<4000,"Low Salary", IF(HR[[#This Row],[MonthlyIncome]]<8000,"Medium Salary","High Salary")) -> Low Salary
A13: 29 | B13: No | C13: Travel_Rarely | D13: 153 | E13: Research & Development | F13: 15 | G13: 2 | H13: Life Sciences | I13: 1 | J13: 15 | K13: 4 | L13: Female | M13: 49 | N13: 2 | O13: 2 | P13: Laboratory Technician | Q13: 3 | R13: Single | S13: 4193 | T13: 12682 | U13: 0 | V13: Y | W13: Yes | X13: 12 | Y13: 3 | Z13: 4 | AA13: 80 | AB13: 0 | AC13: 10 | AD13: 3 | AE13: 3 | AF13: 9 | AG13: 5 | AH13: 0 | AI13: 8 | AJ13: =IF(HR[[#This Row],[OverTime]]="Yes",1,0) -> 1 | AK13: =IF(HR[[#This Row],[JobSatisfaction]]<=2,1,0) -> 0 | AL13: =IF(HR[[#This Row],[WorkLifeBalance]]<=2,1,0) -> 0 | AM13: =IF(HR[[#This Row],[MonthlyIncome]]<AVERAGE(HR[MonthlyIncome]),1,0) -> 1 | AN13: =IF(HR[[#This Row],[EnvironmentSatisfaction]]<=2,1,0) -> 0 | AO13: =IF(HR[[#This Row],[YearsSinceLastPromotion]]>4,1,0) -> 0 | AP13: =(HR[[#This Row],[OverTimeFlag]]*1.5+HR[[#This Row],[LowJobSatisFlag]]*2.5+HR[[#This Row],[LowWLBFlag]]*2+HR[[#This Row],[LowSalaryFlag]]*1.5+HR[[#This Row],[LowEnviFlag]]*2+HR[[#This Row],[LowProFlag]]*0.5)/10 -> 0.3 | AQ13: =IF(A13>=_xlfn.PERCENTILE.INC($A$2:$A$1000,0.8),"High Risk", IF(HR[[#This Row],[AttritionRiskScore]]>=_xlfn.PERCENTILE.INC($AP$2:$AP$1000,0.5),"Medium Risk","Low Risk")) -> Low Risk | AR13: =(HR[[#This Row],[OverTimeFlag]]*4+HR[[#This Row],[LowWLBFlag]]*3+HR[[#This Row],[LowJobSatisFlag]]*2+HR[[#This Row],[LowProFlag]]*1)/10 -> 0.4 | AS13: =IF(AR13>=0.7,"High Burnout",IF(AR13>=0.4,"Medium Burnout","Low Burnout")) -> Medium Burnout | AT13: =IF(HR[[#This Row],[YearsSinceLastPromotion]]>4,"High Stagnation", IF(HR[[#This Row],[YearsSinceLastPromotion]]>=3,"Medium Stagnation","Low Stagnation")) -> Low Stagnation | AU13: =IF(HR[[#This Row],[MonthlyIncome]]<4000,"Low Salary", IF(HR[[#This Row],[MonthlyIncome]]<8000,"Medium Salary","High Salary")) -> Medium Salary
... A1471: 34 | B1471: No | C1471: Travel_Rarely | D1471: 628 | E1471: Research & Development | F1471: 8 | G1471: 3 | H1471: Medical | I1471: 1 | J1471: 2068 | K1471: 2 | L1471: Male | M1471: 82 | N1471: 4 | O1471: 2 | P1471: Laboratory Technician | Q1471: 3 | R1471: Married | S1471: 4404 | T1471: 10228 | U1471: 2 | V1471: Y | W1471: No | X1471: 12 | Y1471: 3 | Z1471: 1 | AA1471: 80 | AB1471: 0 | AC1471: 6 | AD1471: 3 | AE1471: 4 | AF1471: 4 | AG1471: 3 | AH1471: 1 | AI1471: 2 | AJ1471: =IF(HR[[#This Row],[OverTime]]="Yes",1,0) -> 0 | AK1471: =IF(HR[[#This Row],[JobSatisfaction]]<=2,1,0) -> 0 | AL1471: =IF(HR[[#This Row],[WorkLifeBalance]]<=2,1,0) -> 0 | AM1471: =IF(HR[[#This Row],[MonthlyIncome]]<AVERAGE(HR[MonthlyIncome]),1,0) -> 1 | AN1471: =IF(HR[[#This Row],[EnvironmentSatisfaction]]<=2,1,0) -> 1 | AO1471: =IF(HR[[#This Row],[YearsSinceLastPromotion]]>4,1,0) -> 0 | AP1471: =(HR[[#This Row],[OverTimeFlag]]*1.5+HR[[#This Row],[LowJobSatisFlag]]*2.5+HR[[#This Row],[LowWLBFlag]]*2+HR[[#This Row],[LowSalaryFlag]]*1.5+HR[[#This Row],[LowEnviFlag]]*2+HR[[#This Row],[LowProFlag]]*0.5)/10 -> 0.35 | AQ1471: =IF(A1471>=_xlfn.PERCENTILE.INC($A$2:$A$1000,0.8),"High Risk", IF(HR[[#This Row],[AttritionRiskScore]]>=_xlfn.PERCENTILE.INC($AP$2:$AP$1000,0.5),"Medium Risk","Low Risk")) -> Medium Risk | AR1471: =(HR[[#This Row],[OverTimeFlag]]*4+HR[[#This Row],[LowWLBFlag]]*3+HR[[#This Row],[LowJobSatisFlag]]*2+HR[[#This Row],[LowProFlag]]*1)/10 -> 0 | AS1471: =IF(AR1471>=0.7,"High Burnout",IF(AR1471>=0.4,"Medium Burnout","Low Burnout")) -> Low Burnout | AT1471: =IF(HR[[#This Row],[YearsSinceLastPromotion]]>4,"High Stagnation", IF(HR[[#This Row],[YearsSinceLastPromotion]]>=3,"Medium Stagnation","Low Stagnation")) -> Low Stagnation | AU1471: =IF(HR[[#This Row],[MonthlyIncome]]<4000,"Low Salary", IF(HR[[#This Row],[MonthlyIncome]]<8000,"Medium Salary","High Salary")) -> Medium Salary

Sheet HR_Data
A1: Age | B1: AgeGroup | C1: Attrition | D1: AttritionRiskScore | E1: BurnoutScore | F1: BusinessTravel | G1: DailyRate | H1: Department | I1: DistanceFromHome | J1: EarlyLeaver | K1: Education | L1: EducationField | M1: EmployeeCount | N1: EmployeeNumber | O1: LowEnvironmentFlag | P1: EnvironmentSatisfaction | Q1: Gender | R1: HourlyRate | S1: JobInvolvement | T1: JobLevel | U1: JobRole | V1: JobSatisfaction | W1: MaritalStatus | X1: MonthlyIncome | Y1: RiskFlag | Z1: SalaryCategory | AA1: OvertimeFlag | AB1: LowSatisfactionFlag | AC1: LowWorkLifeBalanceFlag | AD1: LowSalaryFlag | AE1: MonthlyRate | AF1: NumCompaniesWorked | AG1: Over18 | AH1: OverTime | AI1: PercentSalaryHike | AJ1: PerformanceRating | AK1: RelationshipSatisfaction | AL1: RiskScore2 | AM1: RiskCategory | AN1: StandardHours | AO1: StockOptionLevel | AP1: TotalWorkingYears | AQ1: TrainingTimesLastYear | AR1: WorkLifeBalance | AS1: YearsAtCompany | AT1: YearsInCurrentRole | AU1: YearsSinceLastPromotion | AV1: YearsWithCurrManager | AW1: Column1
A2: 41 | B2: =IF(HR_Data[[#This Row],[Age]]<25,"<25", IF(HR_Data[[#This Row],[Age]]<35,"25–34", IF(HR_Data[[#This Row],[Age]]<45,"35–44", IF(HR_Data[[#This Row],[Age]]<55,"45–54","55+")))) -> 35–44 | C2: Yes | D2: =(HR[[#This Row],[OverTimeFlag]]*3+HR[[#This Row],[LowJobSatisFlag]]*5+HR[[#This Row],[LowWLBFlag]]*4+HR[[#This Row],[LowSalaryFlag]]*3+HR[[#This Row],[LowEnviFlag]]*4+HR[[#This Row],[LowProFlag]]*1) -> 14 | E2: =HR_Data[[#This Row],[OvertimeFlag]] + HR_Data[[#This Row],[LowSatisfactionFlag]] + HR_Data[[#This Row],[LowWorkLifeBalanceFlag]] -> 2 | F2: Travel_Rarely | G2: 1102 | H2: Sales | I2: 1 | J2: =IF(AND(HR_Data[[#This Row],[Attrition]]="Yes",HR_Data[[#This Row],[YearsAtCompany]]<2),"Yes","No") -> No | K2: 2 | L2: Life Sciences | M2: 1 | N2: 1 | P2: 2 | Q2: Female | R2: 94 | S2: 3 | T2: 2 | U2: Sales Executive | V2: 4 | W2: Single | X2: 5993 | Y2: =IF(AND(HR_Data[[#This Row],[OverTime]]="Yes",HR_Data[[#This Row],[JobSatisfaction]]<=2,HR_Data[[#This Row],[MonthlyIncome]]<AVERAGE(HR_Data[MonthlyIncome])), "High Risk", IF(OR(HR_Data[[#This Row],[OverTime]]="Yes",HR_Data[[#This Row],[JobSatisfaction]]<=2), "Medium Risk", "Low Risk")) -> Medium Risk | Z2: =IF(HR_Data[[#This Row],[MonthlyIncome]]<3000,"Low",IF(HR_Data[[#This Row],[MonthlyIncome]]<7000,"Medium","High")) -> Medium | AA2: =IF(HR_Data[[#This Row],[OverTime]]="Yes",1,0) -> 1 | AB2: =IF(HR_Data[[#This Row],[JobSatisfaction]]<=2,1,0) -> 0 | AC2: =IF(HR_Data[[#This Row],[WorkLifeBalance]]<=2,1,0) -> 1 | AD2: =IF(HR_Data[[#This Row],[MonthlyIncome]]<AVERAGE(HR_Data[MonthlyIncome]),1,0) -> 1 | AE2: 19479 | AF2: 8 | AG2: Y | AH2: Yes | AI2: 11 | AJ2: 3 | AK2: 1 | AL2: =IF(HR_Data[[#This Row],[OverTime]]="Yes",2,0) +IF(HR_Data[[#This Row],[WorkLifeBalance]]<=2,2,0) +IF(HR_Data[[#This Row],[MonthlyIncome]]<5000,2,0) +IF(HR_Data[[#This Row],[JobSatisfaction]]<=2,1,0) +IF(HR_Data[[#This Row],[EnvironmentSatisfaction]]<=2,1,0) +IF(HR_Data[[#This Row],[YearsAtCompany]]<2,2,0) -> 5 | AM2: =IF(HR_Data[[#This Row],[RiskScore2]]>=6,"High", IF(HR_Data[[#This Row],[RiskScore2]]>=3,"Medium","Low")) -> Medium | AN2: 80 | AO2: 0 | AP2: 8 | AQ2: 0 | AR2: 1 | AS2: 6 | AT2: 4 | AU2: 0 | AV2: 5
A3: 49 | B3: =IF(HR_Data[[#This Row],[Age]]<25,"<25", IF(HR_Data[[#This Row],[Age]]<35,"25–34", IF(HR_Data[[#This Row],[Age]]<45,"35–44", IF(HR_Data[[#This Row],[Age]]<55,"45–54","55+")))) -> 45–54 | C3: No | D3: =(HR[[#This Row],[OverTimeFlag]]*3+HR[[#This Row],[LowJobSatisFlag]]*5+HR[[#This Row],[LowWLBFlag]]*4+HR[[#This Row],[LowSalaryFlag]]*3+HR[[#This Row],[LowEnviFlag]]*4+HR[[#This Row],[LowProFlag]]*1) -> 8 | E3: =HR_Data[[#This Row],[OvertimeFlag]] + HR_Data[[#This Row],[LowSatisfactionFlag]] + HR_Data[[#This Row],[LowWorkLifeBalanceFlag]] -> 1 | F3: Travel_Frequently | G3: 279 | H3: Research & Development | I3: 8 | J3: =IF(AND(HR_Data[[#This Row],[Attrition]]="Yes",HR_Data[[#This Row],[YearsAtCompany]]<2),"Yes","No") -> No | K3: 1 | L3: Life Sciences | M3: 1 | N3: 2 | P3: 3 | Q3: Male | R3: 61 | S3: 2 | T3: 2 | U3: Research Scientist | V3: 2 | W3: Married | X3: 5130 | Y3: =IF(AND(HR_Data[[#This Row],[OverTime]]="Yes",HR_Data[[#This Row],[JobSatisfaction]]<=2,HR_Data[[#This Row],[MonthlyIncome]]<AVERAGE(HR_Data[MonthlyIncome])), "High Risk", IF(OR(HR_Data[[#This Row],[OverTime]]="Yes",HR_Data[[#This Row],[JobSatisfaction]]<=2), "Medium Risk", "Low Risk")) -> Medium Risk | Z3: =IF(HR_Data[[#This Row],[MonthlyIncome]]<3000,"Low",IF(HR_Data[[#This Row],[MonthlyIncome]]<7000,"Medium","High")) -> Medium | AA3: =IF(HR_Data[[#This Row],[OverTime]]="Yes",1,0) -> 0 | AB3: =IF(HR_Data[[#This Row],[JobSatisfaction]]<=2,1,0) -> 1 | AC3: =IF(HR_Data[[#This Row],[WorkLifeBalance]]<=2,1,0) -> 0 | AD3: =IF(HR_Data[[#This Row],[MonthlyIncome]]<AVERAGE(HR_Data[MonthlyIncome]),1,0) -> 1 | AE3: 24907 | AF3: 1 | AG3: Y | AH3: No | AI3: 23 | AJ3: 4 | AK3: 4 | AL3: =IF(HR_Data[[#This Row],[OverTime]]="Yes",2,0) +IF(HR_Data[[#This Row],[WorkLifeBalance]]<=2,2,0) +IF(HR_Data[[#This Row],[MonthlyIncome]]<5000,2,0) +IF(HR_Data[[#This Row],[JobSatisfaction]]<=2,1,0) +IF(HR_Data[[#This Row],[EnvironmentSatisfaction]]<=2,1,0) +IF(HR_Data[[#This Row],[YearsAtCompany]]<2,2,0) -> 1 | AM3: =IF(HR_Data[[#This Row],[RiskScore2]]>=6,"High", IF(HR_Data[[#This Row],[RiskScore2]]>=3,"Medium","Low")) -> Low | AN3: 80 | AO3: 1 | AP3: 10 | AQ3: 3 | AR3: 3 | AS3: 10 | AT3: 7 | AU3: 1 | AV3: 7
A4: 37 | B4: =IF(HR_Data[[#This Row],[Age]]<25,"<25", IF(HR_Data[[#This Row],[Age]]<35,"25–34", IF(HR_Data[[#This Row],[Age]]<45,"35–44", IF(HR_Data[[#This Row],[Age]]<55,"45–54","55+")))) -> 35–44 | C4: Yes | D4: =(HR[[#This Row],[OverTimeFlag]]*3+HR[[#This Row],[LowJobSatisFlag]]*5+HR[[#This Row],[LowWLBFlag]]*4+HR[[#This Row],[LowSalaryFlag]]*3+HR[[#This Row],[LowEnviFlag]]*4+HR[[#This Row],[LowProFlag]]*1) -> 6 | E4: =HR_Data[[#This Row],[OvertimeFlag]] + HR_Data[[#This Row],[LowSatisfactionFlag]] + HR_Data[[#This Row],[LowWorkLifeBalanceFlag]] -> 1 | F4: Travel_Rarely | G4: 1373 | H4: Research & Development | I4: 2 | J4: =IF(AND(HR_Data[[#This Row],[Attrition]]="Yes",HR_Data[[#This Row],[YearsAtCompany]]<2),"Yes","No") -> Yes | K4: 2 | L4: Other | M4: 1 | N4: 4 | P4: 4 | Q4: Male | R4: 92 | S4: 2 | T4: 1 | U4: Laboratory Technician | V4: 3 | W4: Single | X4: 2090 | Y4: =IF(AND(HR_Data[[#This Row],[OverTime]]="Yes",HR_Data[[#This Row],[JobSatisfaction]]<=2,HR_Data[[#This Row],[MonthlyIncome]]<AVERAGE(HR_Data[MonthlyIncome])), "High Risk", IF(OR(HR_Data[[#This Row],[OverTime]]="Yes",HR_Data[[#This Row],[JobSatisfaction]]<=2), "Medium Risk", "Low Risk")) -> Medium Risk | Z4: =IF(HR_Data[[#This Row],[MonthlyIncome]]<3000,"Low",IF(HR_Data[[#This Row],[MonthlyIncome]]<7000,"Medium","High")) -> Low | AA4: =IF(HR_Data[[#This Row],[OverTime]]="Yes",1,0) -> 1 | AB4: =IF(HR_Data[[#This Row],[JobSatisfaction]]<=2,1,0) -> 0 | AC4: =IF(HR_Data[[#This Row],[WorkLifeBalance]]<=2,1,0) -> 0 | AD4: =IF(HR_Data[[#This Row],[MonthlyIncome]]<AVERAGE(HR_Data[MonthlyIncome]),1,0) -> 1 | AE4: 2396 | AF4: 6 | AG4: Y | AH4: Yes | AI4: 15 | AJ4: 3 | AK4: 2 | AL4: =IF(HR_Data[[#This Row],[OverTime]]="Yes",2,0) +IF(HR_Data[[#This Row],[WorkLifeBalance]]<=2,2,0) +IF(HR_Data[[#This Row],[MonthlyIncome]]<5000,2,0) +IF(HR_Data[[#This Row],[JobSatisfaction]]<=2,1,0) +IF(HR_Data[[#This Row],[EnvironmentSatisfaction]]<=2,1,0) +IF(HR_Data[[#This Row],[YearsAtCompany]]<2,2,0) -> 6 | AM4: =IF(HR_Data[[#This Row],[RiskScore2]]>=6,"High", IF(HR_Data[[#This Row],[RiskScore2]]>=3,"Medium","Low")) -> High | AN4: 80 | AO4: 0 | AP4: 7 | AQ4: 3 | AR4: 3 | AS4: 0 | AT4: 0 | AU4: 0 | AV4: 0
A5: 33 | B5: =IF(HR_Data[[#This Row],[Age]]<25,"<25", IF(HR_Data[[#This Row],[Age]]<35,"25–34", IF(HR_Data[[#This Row],[Age]]<45,"35–44", IF(HR_Data[[#This Row],[Age]]<55,"45–54","55+")))) -> 25–34 | C5: No | D5: =(HR[[#This Row],[OverTimeFlag]]*3+HR[[#This Row],[LowJobSatisFlag]]*5+HR[[#This Row],[LowWLBFlag]]*4+HR[[#This Row],[LowSalaryFlag]]*3+HR[[#This Row],[LowEnviFlag]]*4+HR[[#This Row],[LowProFlag]]*1) -> 6 | E5: =HR_Data[[#This Row],[OvertimeFlag]] + HR_Data[[#This Row],[LowSatisfactionFlag]] + HR_Data[[#This Row],[LowWorkLifeBalanceFlag]] -> 1 | F5: Travel_Frequently | G5: 1392 | H5: Research & Development | I5: 3 | J5: =IF(AND(HR_Data[[#This Row],[Attrition]]="Yes",HR_Data[[#This Row],[YearsAtCompany]]<2),"Yes","No") -> No | K5: 4 | L5: Life Sciences | M5: 1 | N5: 5 | P5: 4 | Q5: Female | R5: 56 | S5: 3 | T5: 1 | U5: Research Scientist | V5: 3 | W5: Married | X5: 2909 | Y5: =IF(AND(HR_Data[[#This Row],[OverTime]]="Yes",HR_Data[[#This Row],[JobSatisfaction]]<=2,HR_Data[[#This Row],[MonthlyIncome]]<AVERAGE(HR_Data[MonthlyIncome])), "High Risk", IF(OR(HR_Data[[#This Row],[OverTime]]="Yes",HR_Data[[#This Row],[JobSatisfaction]]<=2), "Medium Risk", "Low Risk")) -> Medium Risk | Z5: =IF(HR_Data[[#This Row],[MonthlyIncome]]<3000,"Low",IF(HR_Data[[#This Row],[MonthlyIncome]]<7000,"Medium","High")) -> Low | AA5: =IF(HR_Data[[#This Row],[OverTime]]="Yes",1,0) -> 1 | AB5: =IF(HR_Data[[#This Row],[JobSatisfaction]]<=2,1,0) -> 0 | AC5: =IF(HR_Data[[#This Row],[WorkLifeBalance]]<=2,1,0) -> 0 | AD5: =IF(HR_Data[[#This Row],[MonthlyIncome]]<AVERAGE(HR_Data[MonthlyIncome]),1,0) -> 1 | AE5: 23159 | AF5: 1 | AG5: Y | AH5: Yes | AI5: 11 | AJ5: 3 | AK5: 3 | AL5: =IF(HR_Data[[#This Row],[OverTime]]="Yes",2,0) +IF(HR_Data[[#This Row],[WorkLifeBalance]]<=2,2,0) +IF(HR_Data[[#This Row],[MonthlyIncome]]<5000,2,0) +IF(HR_Data[[#This Row],[JobSatisfaction]]<=2,1,0) +IF(HR_Data[[#This Row],[EnvironmentSatisfaction]]<=2,1,0) +IF(HR_Data[[#This Row],[YearsAtCompany]]<2,2,0) -> 4 | AM5: =IF(HR_Data[[#This Row],[RiskScore2]]>=6,"High", IF(HR_Data[[#This Row],[RiskScore2]]>=3,"Medium","Low")) -> Medium | AN5: 80 | AO5: 0 | AP5: 8 | AQ5: 3 | AR5: 3 | AS5: 8 | AT5: 7 | AU5: 3 | AV5: 0
A6: 27 | B6: =IF(HR_Data[[#This Row],[Age]]<25,"<25", IF(HR_Data[[#This Row],[Age]]<35,"25–34", IF(HR_Data[[#This Row],[Age]]<45,"35–44", IF(HR_Data[[#This Row],[Age]]<55,"45–54","55+")))) -> 25–34 | C6: No | D6: =(HR[[#This Row],[OverTimeFlag]]*3+HR[[#This Row],[LowJobSatisFlag]]*5+HR[[#This Row],[LowWLBFlag]]*4+HR[[#This Row],[LowSalaryFlag]]*3+HR[[#This Row],[LowEnviFlag]]*4+HR[[#This Row],[LowProFlag]]*1) -> 12 | E6: =HR_Data[[#This Row],[OvertimeFlag]] + HR_Data[[#This Row],[LowSatisfactionFlag]] + HR_Data[[#This Row],[LowWorkLifeBalanceFlag]] -> 1 | F6: Travel_Rarely | G6: 591 | H6: Research & Development | I6: 2 | J6: =IF(AND(HR_Data[[#This Row],[Attrition]]="Yes",HR_Data[[#This Row],[YearsAtCompany]]<2),"Yes","No") -> No | K6: 1 | L6: Medical | M6: 1 | N6: 7 | P6: 1 | Q6: Male | R6: 40 | S6: 3 | T6: 1 | U6: Laboratory Technician | V6: 2 | W6: Married | X6: 3468 | Y6: =IF(AND(HR_Data[[#This Row],[OverTime]]="Yes",HR_Data[[#This Row],[JobSatisfaction]]<=2,HR_Data[[#This Row],[MonthlyIncome]]<AVERAGE(HR_Data[MonthlyIncome])), "High Risk", IF(OR(HR_Data[[#This Row],[OverTime]]="Yes",HR_Data[[#This Row],[JobSatisfaction]]<=2), "Medium Risk", "Low Risk")) -> Medium Risk | Z6: =IF(HR_Data[[#This Row],[MonthlyIncome]]<3000,"Low",IF(HR_Data[[#This Row],[MonthlyIncome]]<7000,"Medium","High")) -> Medium | AA6: =IF(HR_Data[[#This Row],[OverTime]]="Yes",1,0) -> 0 | AB6: =IF(HR_Data[[#This Row],[JobSatisfaction]]<=2,1,0) -> 1 | AC6: =IF(HR_Data[[#This Row],[WorkLifeBalance]]<=2,1,0) -> 0 | AD6: =IF(HR_Data[[#This Row],[MonthlyIncome]]<AVERAGE(HR_Data[MonthlyIncome]),1,0) -> 1 | AE6: 16632 | AF6: 9 | AG6: Y | AH6: No | AI6: 12 | AJ6: 3 | AK6: 4 | AL6: =IF(HR_Data[[#This Row],[OverTime]]="Yes",2,0) +IF(HR_Data[[#This Row],[WorkLifeBalance]]<=2,2,0) +IF(HR_Data[[#This Row],[MonthlyIncome]]<5000,2,0) +IF(HR_Data[[#This Row],[JobSatisfaction]]<=2,1,0) +IF(HR_Data[[#This Row],[EnvironmentSatisfaction]]<=2,1,0) +IF(HR_Data[[#This Row],[YearsAtCompany]]<2,2,0) -> 4 | AM6: =IF(HR_Data[[#This Row],[RiskScore2]]>=6,"High", IF(HR_Data[[#This Row],[RiskScore2]]>=3,"Medium","Low")) -> Medium | AN6: 80 | AO6: 1 | AP6: 6 | AQ6: 3 | AR6: 3 | AS6: 2 | AT6: 2 | AU6: 2 | AV6: 2
A7: 32 | B7: =IF(HR_Data[[#This Row],[Age]]<25,"<25", IF(HR_Data[[#This Row],[Age]]<35,"25–34", IF(HR_Data[[#This Row],[Age]]<45,"35–44", IF(HR_Data[[#This Row],[Age]]<55,"45–54","55+")))) -> 25–34 | C7: No | D7: =(HR[[#This Row],[OverTimeFlag]]*3+HR[[#This Row],[LowJobSatisFlag]]*5+HR[[#This Row],[LowWLBFlag]]*4+HR[[#This Row],[LowSalaryFlag]]*3+HR[[#This Row],[LowEnviFlag]]*4+HR[[#This Row],[LowProFlag]]*1) -> 7 | E7: =HR_Data[[#This Row],[OvertimeFlag]] + HR_Data[[#This Row],[LowSatisfactionFlag]] + HR_Data[[#This Row],[LowWorkLifeBalanceFlag]] -> 1 | F7: Travel_Frequently | G7: 1005 | H7: Research & Development | I7: 2 | J7: =IF(AND(HR_Data[[#This Row],[Attrition]]="Yes",HR_Data[[#This Row],[YearsAtCompany]]<2),"Yes","No") -> No | K7: 2 | L7: Life Sciences | M7: 1 | N7: 8 | P7: 4 | Q7: Male | R7: 79 | S7: 3 | T7: 1 | U7: Laboratory Technician | V7: 4 | W7: Single | X7: 3068 | Y7: =IF(AND(HR_Data[[#This Row],[OverTime]]="Yes",HR_Data[[#This Row],[JobSatisfaction]]<=2,HR_Data[[#This Row],[MonthlyIncome]]<AVERAGE(HR_Data[MonthlyIncome])), "High Risk", IF(OR(HR_Data[[#This Row],[OverTime]]="Yes",HR_Data[[#This Row],[JobSatisfaction]]<=2), "Medium Risk", "Low Risk")) -> Low Risk | Z7: =IF(HR_Data[[#This Row],[MonthlyIncome]]<3000,"Low",IF(HR_Data[[#This Row],[MonthlyIncome]]<7000,"Medium","High")) -> Medium | AA7: =IF(HR_Data[[#This Row],[OverTime]]="Yes",1,0) -> 0 | AB7: =IF(HR_Data[[#This Row],[JobSatisfaction]]<=2,1,0) -> 0 | AC7: =IF(HR_Data[[#This Row],[WorkLifeBalance]]<=2,1,0) -> 1 | AD7: =IF(HR_Data[[#This Row],[MonthlyIncome]]<AVERAGE(HR_Data[MonthlyIncome]),1,0) -> 1 | AE7: 11864 | AF7: 0 | AG7: Y | AH7: No | AI7: 13 | AJ7: 3 | AK7: 3 | AL7: =IF(HR_Data[[#This Row],[OverTime]]="Yes",2,0) +IF(HR_Data[[#This Row],[WorkLifeBalance]]<=2,2,0) +IF(HR_Data[[#This Row],[MonthlyIncome]]<5000,2,0) +IF(HR_Data[[#This Row],[JobSatisfaction]]<=2,1,0) +IF(HR_Data[[#This Row],[EnvironmentSatisfaction]]<=2,1,0) +IF(HR_Data[[#This Row],[YearsAtCompany]]<2,2,0) -> 4 | AM7: =IF(HR_Data[[#This Row],[RiskScore2]]>=6,"High", IF(HR_Data[[#This Row],[RiskScore2]]>=3,"Medium","Low")) -> Medium | AN7: 80 | AO7: 0 | AP7: 8 | AQ7: 2 | AR7: 2 | AS7: 7 | AT7: 7 | AU7: 3 | AV7: 6
A8: 59 | B8: =IF(HR_Data[[#This Row],[Age]]<25,"<25", IF(HR_Data[[#This Row],[Age]]<35,"25–34", IF(HR_Data[[#This Row],[Age]]<45,"35–44", IF(HR_Data[[#This Row],[Age]]<55,"45–54","55+")))) -> 55+ | C8: No | D8: =(HR[[#This Row],[OverTimeFlag]]*3+HR[[#This Row],[LowJobSatisFlag]]*5+HR[[#This Row],[LowWLBFlag]]*4+HR[[#This Row],[LowSalaryFlag]]*3+HR[[#This Row],[LowEnviFlag]]*4+HR[[#This Row],[LowProFlag]]*1) -> 15 | E8: =HR_Data[[#This Row],[OvertimeFlag]] + HR_Data[[#This Row],[LowSatisfactionFlag]] + HR_Data[[#This Row],[LowWorkLifeBalanceFlag]] -> 3 | F8: Travel_Rarely | G8: 1324 | H8: Research & Development | I8: 3 | J8: =IF(AND(HR_Data[[#This Row],[Attrition]]="Yes",HR_Data[[#This Row],[YearsAtCompany]]<2),"Yes","No") -> No | K8: 3 | L8: Medical | M8: 1 | N8: 10 | P8: 3 | Q8: Female | R8: 81 | S8: 4 | T8: 1 | U8: Laboratory Technician | V8: 1 | W8: Married | X8: 2670 | Y8: =IF(AND(HR_Data[[#This Row],[OverTime]]="Yes",HR_Data[[#This Row],[JobSatisfaction]]<=2,HR_Data[[#This Row],[MonthlyIncome]]<AVERAGE(HR_Data[MonthlyIncome])), "High Risk", IF(OR(HR_Data[[#This Row],[OverTime]]="Yes",HR_Data[[#This Row],[JobSatisfaction]]<=2), "Medium Risk", "Low Risk")) -> High Risk | Z8: =IF(HR_Data[[#This Row],[MonthlyIncome]]<3000,"Low",IF(HR_Data[[#This Row],[MonthlyIncome]]<7000,"Medium","High")) -> Low | AA8: =IF(HR_Data[[#This Row],[OverTime]]="Yes",1,0) -> 1 | AB8: =IF(HR_Data[[#This Row],[JobSatisfaction]]<=2,1,0) -> 1 | AC8: =IF(HR_Data[[#This Row],[WorkLifeBalance]]<=2,1,0) -> 1 | AD8: =IF(HR_Data[[#This Row],[MonthlyIncome]]<AVERAGE(HR_Data[MonthlyIncome]),1,0) -> 1 | AE8: 9964 | AF8: 4 | AG8: Y | AH8: Yes | AI8: 20 | AJ8: 4 | AK8: 1 | AL8: =IF(HR_Data[[#This Row],[OverTime]]="Yes",2,0) +IF(HR_Data[[#This Row],[WorkLifeBalance]]<=2,2,0) +IF(HR_Data[[#This Row],[MonthlyIncome]]<5000,2,0) +IF(HR_Data[[#This Row],[JobSatisfaction]]<=2,1,0) +IF(HR_Data[[#This Row],[EnvironmentSatisfaction]]<=2,1,0) +IF(HR_Data[[#This Row],[YearsAtCompany]]<2,2,0) -> 9 | AM8: =IF(HR_Data[[#This Row],[RiskScore2]]>=6,"High", IF(HR_Data[[#This Row],[RiskScore2]]>=3,"Medium","Low")) -> High | AN8: 80 | AO8: 3 | AP8: 12 | AQ8: 3 | AR8: 2 | AS8: 1 | AT8: 0 | AU8: 0 | AV8: 0
A9: 30 | B9: =IF(HR_Data[[#This Row],[Age]]<25,"<25", IF(HR_Data[[#This Row],[Age]]<35,"25–34", IF(HR_Data[[#This Row],[Age]]<45,"35–44", IF(HR_Data[[#This Row],[Age]]<55,"45–54","55+")))) -> 25–34 | C9: No | D9: =(HR[[#This Row],[OverTimeFlag]]*3+HR[[#This Row],[LowJobSatisFlag]]*5+HR[[#This Row],[LowWLBFlag]]*4+HR[[#This Row],[LowSalaryFlag]]*3+HR[[#This Row],[LowEnviFlag]]*4+HR[[#This Row],[LowProFlag]]*1) -> 3 | E9: =HR_Data[[#This Row],[OvertimeFlag]] + HR_Data[[#This Row],[LowSatisfactionFlag]] + HR_Data[[#This Row],[LowWorkLifeBalanceFlag]] -> 0 | F9: Travel_Rarely | G9: 1358 | H9: Research & Development | I9: 24 | J9: =IF(AND(HR_Data[[#This Row],[Attrition]]="Yes",HR_Data[[#This Row],[YearsAtCompany]]<2),"Yes","No") -> No | K9: 1 | L9: Life Sciences | M9: 1 | N9: 11 | P9: 4 | Q9: Male | R9: 67 | S9: 3 | T9: 1 | U9: Laboratory Technician | V9: 3 | W9: Divorced | X9: 2693 | Y9: =IF(AND(HR_Data[[#This Row],[OverTime]]="Yes",HR_Data[[#This Row],[JobSatisfaction]]<=2,HR_Data[[#This Row],[MonthlyIncome]]<AVERAGE(HR_Data[MonthlyIncome])), "High Risk", IF(OR(HR_Data[[#This Row],[OverTime]]="Yes",HR_Data[[#This Row],[JobSatisfaction]]<=2), "Medium Risk", "Low Risk")) -> Low Risk | Z9: =IF(HR_Data[[#This Row],[MonthlyIncome]]<3000,"Low",IF(HR_Data[[#This Row],[MonthlyIncome]]<7000,"Medium","High")) -> Low | AA9: =IF(HR_Data[[#This Row],[OverTime]]="Yes",1,0) -> 0 | AB9: =IF(HR_Data[[#This Row],[JobSatisfaction]]<=2,1,0) -> 0 | AC9: =IF(HR_Data[[#This Row],[WorkLifeBalance]]<=2,1,0) -> 0 | AD9: =IF(HR_Data[[#This Row],[MonthlyIncome]]<AVERAGE(HR_Data[MonthlyIncome]),1,0) -> 1 | AE9: 13335 | AF9: 1 | AG9: Y | AH9: No | AI9: 22 | AJ9: 4 | AK9: 2 | AL9: =IF(HR_Data[[#This Row],[OverTime]]="Yes",2,0) +IF(HR_Data[[#This Row],[WorkLifeBalance]]<=2,2,0) +IF(HR_Data[[#This Row],[MonthlyIncome]]<5000,2,0) +IF(HR_Data[[#This Row],[JobSatisfaction]]<=2,1,0) +IF(HR_Data[[#This Row],[EnvironmentSatisfaction]]<=2,1,0) +IF(HR_Data[[#This Row],[YearsAtCompany]]<2,2,0) -> 4 | AM9: =IF(HR_Data[[#This Row],[RiskScore2]]>=6,"High", IF(HR_Data[[#This Row],[RiskScore2]]>=3,"Medium","Low")) -> Medium | AN9: 80 | AO9: 1 | AP9: 1 | AQ9: 2 | AR9: 3 | AS9: 1 | AT9: 0 | AU9: 0 | AV9: 0
A10: 38 | B10: =IF(HR_Data[[#This Row],[Age]]<25,"<25", IF(HR_Data[[#This Row],[Age]]<35,"25–34", IF(HR_Data[[#This Row],[Age]]<45,"35–44", IF(HR_Data[[#This Row],[Age]]<55,"45–54","55+")))) -> 35–44 | C10: No | D10: =(HR[[#This Row],[OverTimeFlag]]*3+HR[[#This Row],[LowJobSatisFlag]]*5+HR[[#This Row],[LowWLBFlag]]*4+HR[[#This Row],[LowSalaryFlag]]*3+HR[[#This Row],[LowEnviFlag]]*4+HR[[#This Row],[LowProFlag]]*1) -> 0 | E10: =HR_Data[[#This Row],[OvertimeFlag]] + HR_Data[[#This Row],[LowSatisfactionFlag]] + HR_Data[[#This Row],[LowWorkLifeBalanceFlag]] -> 0 | F10: Travel_Frequently | G10: 216 | H10: Research & Development | I10: 23 | J10: =IF(AND(HR_Data[[#This Row],[Attrition]]="Yes",HR_Data[[#This Row],[YearsAtCompany]]<2),"Yes","No") -> No | K10: 3 | L10: Life Sciences | M10: 1 | N10: 12 | P10: 4 | Q10: Male | R10: 44 | S10: 2 | T10: 3 | U10: Manufacturing Director | V10: 3 | W10: Single | X10: 9526 | Y10: =IF(AND(HR_Data[[#This Row],[OverTime]]="Yes",HR_Data[[#This Row],[JobSatisfaction]]<=2,HR_Data[[#This Row],[MonthlyIncome]]<AVERAGE(HR_Data[MonthlyIncome])), "High Risk", IF(OR(HR_Data[[#This Row],[OverTime]]="Yes",HR_Data[[#This Row],[JobSatisfaction]]<=2), "Medium Risk", "Low Risk")) -> Low Risk | Z10: =IF(HR_Data[[#This Row],[MonthlyIncome]]<3000,"Low",IF(HR_Data[[#This Row],[MonthlyIncome]]<7000,"Medium","High")) -> High | AA10: =IF(HR_Data[[#This Row],[OverTime]]="Yes",1,0) -> 0 | AB10: =IF(HR_Data[[#This Row],[JobSatisfaction]]<=2,1,0) -> 0 | AC10: =IF(HR_Data[[#This Row],[WorkLifeBalance]]<=2,1,0) -> 0 | AD10: =IF(HR_Data[[#This Row],[MonthlyIncome]]<AVERAGE(HR_Data[MonthlyIncome]),1,0) -> 0 | AE10: 8787 | AF10: 0 | AG10: Y | AH10: No | AI10: 21 | AJ10: 4 | AK10: 2 | AL10: =IF(HR_Data[[#This Row],[OverTime]]="Yes",2,0) +IF(HR_Data[[#This Row],[WorkLifeBalance]]<=2,2,0) +IF(HR_Data[[#This Row],[MonthlyIncome]]<5000,2,0) +IF(HR_Data[[#This Row],[JobSatisfaction]]<=2,1,0) +IF(HR_Data[[#This Row],[EnvironmentSatisfaction]]<=2,1,0) +IF(HR_Data[[#This Row],[YearsAtCompany]]<2,2,0) -> 0 | AM10: =IF(HR_Data[[#This Row],[RiskScore2]]>=6,"High", IF(HR_Data[[#This Row],[RiskScore2]]>=3,"Medium","Low")) -> Low | AN10: 80 | AO10: 0 | AP10: 10 | AQ10: 2 | AR10: 3 | AS10: 9 | AT10: 7 | AU10: 1 | AV10: 8
A11: 36 | B11: =IF(HR_Data[[#This Row],[Age]]<25,"<25", IF(HR_Data[[#This Row],[Age]]<35,"25–34", IF(HR_Data[[#This Row],[Age]]<45,"35–44", IF(HR_Data[[#This Row],[Age]]<55,"45–54","55+")))) -> 35–44 | C11: No | D11: =(HR[[#This Row],[OverTimeFlag]]*3+HR[[#This Row],[LowJobSatisFlag]]*5+HR[[#This Row],[LowWLBFlag]]*4+HR[[#This Row],[LowSalaryFlag]]*3+HR[[#This Row],[LowEnviFlag]]*4+HR[[#This Row],[LowProFlag]]*1) -> 8 | E11: =HR_Data[[#This Row],[OvertimeFlag]] + HR_Data[[#This Row],[LowSatisfactionFlag]] + HR_Data[[#This Row],[LowWorkLifeBalanceFlag]] -> 1 | F11: Travel_Rarely | G11: 1299 | H11: Research & Development | I11: 27 | J11: =IF(AND(HR_Data[[#This Row],[Attrition]]="Yes",HR_Data[[#This Row],[YearsAtCompany]]<2),"Yes","No") -> No | K11: 3 | L11: Medical | M11: 1 | N11: 13 | P11: 3 | Q11: Male | R11: 94 | S11: 3 | T11: 2 | U11: Healthcare Representative | V11: 3 | W11: Married | X11: 5237 | Y11: =IF(AND(HR_Data[[#This Row],[OverTime]]="Yes",HR_Data[[#This Row],[JobSatisfaction]]<=2,HR_Data[[#This Row],[MonthlyIncome]]<AVERAGE(HR_Data[MonthlyIncome])), "High Risk", IF(OR(HR_Data[[#This Row],[OverTime]]="Yes",HR_Data[[#This Row],[JobSatisfaction]]<=2), "Medium Risk", "Low Risk")) -> Low Risk | Z11: =IF(HR_Data[[#This Row],[MonthlyIncome]]<3000,"Low",IF(HR_Data[[#This Row],[MonthlyIncome]]<7000,"Medium","High")) -> Medium | AA11: =IF(HR_Data[[#This Row],[OverTime]]="Yes",1,0) -> 0 | AB11: =IF(HR_Data[[#This Row],[JobSatisfaction]]<=2,1,0) -> 0 | AC11: =IF(HR_Data[[#This Row],[WorkLifeBalance]]<=2,1,0) -> 1 | AD11: =IF(HR_Data[[#This Row],[MonthlyIncome]]<AVERAGE(HR_Data[MonthlyIncome]),1,0) -> 1 | AE11: 16577 | AF11: 6 | AG11: Y | AH11: No | AI11: 13 | AJ11: 3 | AK11: 2 | AL11: =IF(HR_Data[[#This Row],[OverTime]]="Yes",2,0) +IF(HR_Data[[#This Row],[WorkLifeBalance]]<=2,2,0) +IF(HR_Data[[#This Row],[MonthlyIncome]]<5000,2,0) +IF(HR_Data[[#This Row],[JobSatisfaction]]<=2,1,0) +IF(HR_Data[[#This Row],[EnvironmentSatisfaction]]<=2,1,0) +IF(HR_Data[[#This Row],[YearsAtCompany]]<2,2,0) -> 2 | AM11: =IF(HR_Data[[#This Row],[RiskScore2]]>=6,"High", IF(HR_Data[[#This Row],[RiskScore2]]>=3,"Medium","Low")) -> Low | AN11: 80 | AO11: 2 | AP11: 17 | AQ11: 3 | AR11: 2 | AS11: 7 | AT11: 7 | AU11: 7 | AV11: 7
A12: 35 | B12: =IF(HR_Data[[#This Row],[Age]]<25,"<25", IF(HR_Data[[#This Row],[Age]]<35,"25–34", IF(HR_Data[[#This Row],[Age]]<45,"35–44", IF(HR_Data[[#This Row],[Age]]<55,"45–54","55+")))) -> 35–44 | C12: No | D12: =(HR[[#This Row],[OverTimeFlag]]*3+HR[[#This Row],[LowJobSatisFlag]]*5+HR[[#This Row],[LowWLBFlag]]*4+HR[[#This Row],[LowSalaryFlag]]*3+HR[[#This Row],[LowEnviFlag]]*4+HR[[#This Row],[LowProFlag]]*1) -> 12 | E12: =HR_Data[[#This Row],[OvertimeFlag]] + HR_Data[[#This Row],[LowSatisfactionFlag]] + HR_Data[[#This Row],[LowWorkLifeBalanceFlag]] -> 1 | F12: Travel_Rarely | G12: 809 | H12: Research & Development | I12: 16 | J12: =IF(AND(HR_Data[[#This Row],[Attrition]]="Yes",HR_Data[[#This Row],[YearsAtCompany]]<2),"Yes","No") -> No | K12: 3 | L12: Medical | M12: 1 | N12: 14 | P12: 1 | Q12: Male | R12: 84 | S12: 4 | T12: 1 | U12: Laboratory Technician | V12: 2 | W12: Married | X12: 2426 | Y12: =IF(AND(HR_Data[[#This Row],[OverTime]]="Yes",HR_Data[[#This Row],[JobSatisfaction]]<=2,HR_Data[[#This Row],[MonthlyIncome]]<AVERAGE(HR_Data[MonthlyIncome])), "High Risk", IF(OR(HR_Data[[#This Row],[OverTime]]="Yes",HR_Data[[#This Row],[JobSatisfaction]]<=2), "Medium Risk", "Low Risk")) -> Medium Risk | Z12: =IF(HR_Data[[#This Row],[MonthlyIncome]]<3000,"Low",IF(HR_Data[[#This Row],[MonthlyIncome]]<7000,"Medium","High")) -> Low | AA12: =IF(HR_Data[[#This Row],[OverTime]]="Yes",1,0) -> 0 | AB12: =IF(HR_Data[[#This Row],[JobSatisfaction]]<=2,1,0) -> 1 | AC12: =IF(HR_Data[[#This Row],[WorkLifeBalance]]<=2,1,0) -> 0 | AD12: =IF(HR_Data[[#This Row],[MonthlyIncome]]<AVERAGE(HR_Data[MonthlyIncome]),1,0) -> 1 | AE12: 16479 | AF12: 0 | AG12: Y | AH12: No | AI12: 13 | AJ12: 3 | AK12: 3 | AL12: =IF(HR_Data[[#This Row],[OverTime]]="Yes",2,0) +IF(HR_Data[[#This Row],[WorkLifeBalance]]<=2,2,0) +IF(HR_Data[[#This Row],[MonthlyIncome]]<5000,2,0) +IF(HR_Data[[#This Row],[JobSatisfaction]]<=2,1,0) +IF(HR_Data[[#This Row],[EnvironmentSatisfaction]]<=2,1,0) +IF(HR_Data[[#This Row],[YearsAtCompany]]<2,2,0) -> 4 | AM12: =IF(HR_Data[[#This Row],[RiskScore2]]>=6,"High", IF(HR_Data[[#This Row],[RiskScore2]]>=3,"Medium","Low")) -> Medium | AN12: 80 | AO12: 1 | AP12: 6 | AQ12: 5 | AR12: 3 | AS12: 5 | AT12: 4 | AU12: 0 | AV12: 3
A13: 29 | B13: =IF(HR_Data[[#This Row],[Age]]<25,"<25", IF(HR_Data[[#This Row],[Age]]<35,"25–34", IF(HR_Data[[#This Row],[Age]]<45,"35–44", IF(HR_Data[[#This Row],[Age]]<55,"45–54","55+")))) -> 25–34 | C13: No | D13: =(HR[[#This Row],[OverTimeFlag]]*3+HR[[#This Row],[LowJobSatisFlag]]*5+HR[[#This Row],[LowWLBFlag]]*4+HR[[#This Row],[LowSalaryFlag]]*3+HR[[#This Row],[LowEnviFlag]]*4+HR[[#This Row],[LowProFlag]]*1) -> 6 | E13: =HR_Data[[#This Row],[OvertimeFlag]] + HR_Data[[#This Row],[LowSatisfactionFlag]] + HR_Data[[#This Row],[LowWorkLifeBalanceFlag]] -> 1 | F13: Travel_Rarely | G13: 153 | H13: Research & Development | I13: 15 | J13: =IF(AND(HR_Data[[#This Row],[Attrition]]="Yes",HR_Data[[#This Row],[YearsAtCompany]]<2),"Yes","No") -> No | K13: 2 | L13: Life Sciences | M13: 1 | N13: 15 | P13: 4 | Q13: Female | R13: 49 | S13: 2 | T13: 2 | U13: Laboratory Technician | V13: 3 | W13: Single | X13: 4193 | Y13: =IF(AND(HR_Data[[#This Row],[OverTime]]="Yes",HR_Data[[#This Row],[JobSatisfaction]]<=2,HR_Data[[#This Row],[MonthlyIncome]]<AVERAGE(HR_Data[MonthlyIncome])), "High Risk", IF(OR(HR_Data[[#This Row],[OverTime]]="Yes",HR_Data[[#This Row],[JobSatisfaction]]<=2), "Medium Risk", "Low Risk")) -> Medium Risk | Z13: =IF(HR_Data[[#This Row],[MonthlyIncome]]<3000,"Low",IF(HR_Data[[#This Row],[MonthlyIncome]]<7000,"Medium","High")) -> Medium | AA13: =IF(HR_Data[[#This Row],[OverTime]]="Yes",1,0) -> 1 | AB13: =IF(HR_Data[[#This Row],[JobSatisfaction]]<=2,1,0) -> 0 | AC13: =IF(HR_Data[[#This Row],[WorkLifeBalance]]<=2,1,0) -> 0 | AD13: =IF(HR_Data[[#This Row],[MonthlyIncome]]<AVERAGE(HR_Data[MonthlyIncome]),1,0) -> 1 | AE13: 12682 | AF13: 0 | AG13: Y | AH13: Yes | AI13: 12 | AJ13: 3 | AK13: 4 | AL13: =IF(HR_Data[[#This Row],[OverTime]]="Yes",2,0) +IF(HR_Data[[#This Row],[WorkLifeBalance]]<=2,2,0) +IF(HR_Data[[#This Row],[MonthlyIncome]]<5000,2,0) +IF(HR_Data[[#This Row],[JobSatisfaction]]<=2,1,0) +IF(HR_Data[[#This Row],[EnvironmentSatisfaction]]<=2,1,0) +IF(HR_Data[[#This Row],[YearsAtCompany]]<2,2,0) -> 4 | AM13: =IF(HR_Data[[#This Row],[RiskScore2]]>=6,"High", IF(HR_Data[[#This Row],[RiskScore2]]>=3,"Medium","Low")) -> Medium | AN13: 80 | AO13: 0 | AP13: 10 | AQ13: 3 | AR13: 3 | AS13: 9 | AT13: 5 | AU13: 0 | AV13: 8
... A1471: 34 | B1471: =IF(HR_Data[[#This Row],[Age]]<25,"<25", IF(HR_Data[[#This Row],[Age]]<35,"25–34", IF(HR_Data[[#This Row],[Age]]<45,"35–44", IF(HR_Data[[#This Row],[Age]]<55,"45–54","55+")))) -> 25–34 | C1471: No | D1471: =(HR[[#This Row],[OverTimeFlag]]*3+HR[[#This Row],[LowJobSatisFlag]]*5+HR[[#This Row],[LowWLBFlag]]*4+HR[[#This Row],[LowSalaryFlag]]*3+HR[[#This Row],[LowEnviFlag]]*4+HR[[#This Row],[LowProFlag]]*1) -> 7 | E1471: =HR_Data[[#This Row],[OvertimeFlag]] + HR_Data[[#This Row],[LowSatisfactionFlag]] + HR_Data[[#This Row],[LowWorkLifeBalanceFlag]] -> 0 | F1471: Travel_Rarely | G1471: 628 | H1471: Research & Development | I1471: 8 | J1471: =IF(AND(HR_Data[[#This Row],[Attrition]]="Yes",HR_Data[[#This Row],[YearsAtCompany]]<2),"Yes","No") -> No | K1471: 3 | L1471: Medical | M1471: 1 | N1471: 2068 | P1471: 2 | Q1471: Male | R1471: 82 | S1471: 4 | T1471: 2 | U1471: Laboratory Technician | V1471: 3 | W1471: Married | X1471: 4404 | Y1471: =IF(AND(HR_Data[[#This Row],[OverTime]]="Yes",HR_Data[[#This Row],[JobSatisfaction]]<=2,HR_Data[[#This Row],[MonthlyIncome]]<AVERAGE(HR_Data[MonthlyIncome])), "High Risk", IF(OR(HR_Data[[#This Row],[OverTime]]="Yes",HR_Data[[#This Row],[JobSatisfaction]]<=2), "Medium Risk", "Low Risk")) -> Low Risk | Z1471: =IF(HR_Data[[#This Row],[MonthlyIncome]]<3000,"Low",IF(HR_Data[[#This Row],[MonthlyIncome]]<7000,"Medium","High")) -> Medium | AA1471: =IF(HR_Data[[#This Row],[OverTime]]="Yes",1,0) -> 0 | AB1471: =IF(HR_Data[[#This Row],[JobSatisfaction]]<=2,1,0) -> 0 | AC1471: =IF(HR_Data[[#This Row],[WorkLifeBalance]]<=2,1,0) -> 0 | AD1471: =IF(HR_Data[[#This Row],[MonthlyIncome]]<AVERAGE(HR_Data[MonthlyIncome]),1,0) -> 1 | AE1471: 10228 | AF1471: 2 | AG1471: Y | AH1471: No | AI1471: 12 | AJ1471: 3 | AK1471: 1 | AL1471: =IF(HR_Data[[#This Row],[OverTime]]="Yes",2,0) +IF(HR_Data[[#This Row],[WorkLifeBalance]]<=2,2,0) +IF(HR_Data[[#This Row],[MonthlyIncome]]<5000,2,0) +IF(HR_Data[[#This Row],[JobSatisfaction]]<=2,1,0) +IF(HR_Data[[#This Row],[EnvironmentSatisfaction]]<=2,1,0) +IF(HR_Data[[#This Row],[YearsAtCompany]]<2,2,0) -> 3 | AM1471: =IF(HR_Data[[#This Row],[RiskScore2]]>=6,"High", IF(HR_Data[[#This Row],[RiskScore2]]>=3,"Medium","Low")) -> Medium | AN1471: 80 | AO1471: 0 | AP1471: 6 | AQ1471: 3 | AR1471: 4 | AS1471: 4 | AT1471: 3 | AU1471: 1 | AV1471: 2

Sheet RiskFlag
A1: AttritionRiskScore | B1: AtriRiskCategory | C1: EmployeeNumber | D1: Department | E1: OverTime | F1: SalaryCategory
A2: 0.7 | B2: Medium Risk | C2: 1 | D2: Sales | E2: Yes | F2: Medium
A3: 0.4 | B3: High Risk | C3: 2 | D3: Research & Development | E3: No | F3: Medium
A4: 0.3 | B4: Low Risk | C4: 4 | D4: Research & Development | E4: Yes | F4: Low
A5: 0.3 | B5: Low Risk | C5: 5 | D5: Research & Development | E5: Yes | F5: Low
A6: 0.6 | B6: Medium Risk | C6: 7 | D6: Research & Development | E6: No | F6: Medium | J6: AtriRiskCategory | K6: Count of EmployeeNumber
A7: 0.35 | B7: Medium Risk | C7: 8 | D7: Research & Development | E7: No | F7: Medium | J7: High Risk | K7: 314
A8: 0.75 | B8: High Risk | C8: 10 | D8: Research & Development | E8: Yes | F8: Low | J8: Low Risk | K8: 405
A9: 0.15 | B9: Low Risk | C9: 11 | D9: Research & Development | E9: No | F9: Low | J9: Medium Risk | K9: 751
A10: 0 | B10: Low Risk | C10: 12 | D10: Research & Development | E10: No | F10: High | J10: (blank)
A11: 0.4 | B11: Medium Risk | C11: 13 | D11: Research & Development | E11: No | F11: Medium | J11: Grand Total | K11: 1470
A12: 0.6 | B12: Medium Risk | C12: 14 | D12: Research & Development | E12: No | F12: Low
A13: 0.3 | B13: Low Risk | C13: 15 | D13: Research & Development | E13: Yes | F13: Medium
A14: 0.55 | B14: Medium Risk | C14: 16 | D14: Research & Development | E14: No | F14: Low
A15: 0.35 | B15: Medium Risk | C15: 18 | D15: Research & Development | E15: No | F15: Low | J15: Count of EmployeeNumber | K15: AtriRiskCategory
A16: 0.3 | B16: Low Risk | C16: 19 | D16: Research & Development | E16: Yes | F16: Low | J16: Department | K16: High Risk | L16: Low Risk | M16: Medium Risk | N16: (blank) | O16: Grand Total
A17: 0.5 | B17: Medium Risk | C17: 20 | D17: Research & Development | E17: No | F17: High | J17: Human Resources | K17: 13 | L17: 13 | M17: 37 | O17: 63
A18: 0.95 | B18: Medium Risk | C18: 21 | D18: Research & Development | E18: Yes | F18: Medium | J18: Research & Development | K18: 204 | L18: 253 | M18: 504 | O18: 961 | U18: Count of EmployeeNumber | V18: Department
A19: 0.5 | B19: Medium Risk | C19: 22 | D19: Research & Development | E19: Yes | F19: Low | J19: Sales | K19: 97 | L19: 139 | M19: 210 | O19: 446 | U19: AtriRiskCategory | V19: Human Resources | W19: Research & Development | X19: Sales | Y19: Grand Total
A20: 0.2 | B20: High Risk | C20: 23 | D20: Sales | E20: No | F20: High | J20: (blank) | U20: High Risk | V20: 13 | W20: 204 | X20: 97 | Y20: 314
A21: 0.3 | B21: Low Risk | C21: 24 | D21: Research & Development | E21: Yes | F21: Medium | J21: Grand Total | K21: 314 | L21: 405 | M21: 751 | O21: 1470 | U21: Low Risk | V21: 13 | W21: 253 | X21: 139 | Y21: 405
A22: 0.55 | B22: Medium Risk | C22: 26 | D22: Research & Development | E22: No | F22: Medium | U22: Medium Risk | V22: 37 | W22: 504 | X22: 210 | Y22: 751
A23: 0.4 | B23: Medium Risk | C23: 27 | D23: Sales | E23: No | F23: Medium | U23: Grand Total | V23: 63 | W23: 961 | X23: 446 | Y23: 1470
A24: 0.45 | B24: Medium Risk | C24: 28 | D24: Research & Development | E24: No | F24: High
A25: 0.15 | B25: Low Risk | C25: 30 | D25: Research & Development | E25: No | F25: Low | J25: Count of EmployeeNumber | K25: OverTime
A26: 0.6 | B26: Medium Risk | C26: 31 | D26: Research & Development | E26: No | F26: Low | J26: AtriRiskCategory | K26: No | L26: Yes | M26: (blank) | N26: Grand Total
A27: 0.2 | B27: High Risk | C27: 32 | D27: Research & Development | E27: No | F27: High | J27: High Risk | K27: 221 | L27: 93 | N27: 314
A28: 0.8 | B28: Medium Risk | C28: 33 | D28: Research & Development | E28: Yes | F28: Medium | J28: Low Risk | K28: 313 | L28: 92 | N28: 405
A29: 0.25 | B29: Low Risk | C29: 35 | D29: Sales | E29: No | F29: Medium | J29: Medium Risk | K29: 520 | L29: 231 | N29: 751
A30: 0.25 | B30: Low Risk | C30: 36 | D30: Research & Development | E30: No | F30: High | J30: (blank)
A31: 0.65 | B31: High Risk | C31: 38 | D31: Sales | E31: No | F31: High | J31: Grand Total | K31: 1054 | L31: 416 | N31: 1470
A32: 0.15 | B32: Low Risk | C32: 39 | D32: Research & Development | E32: No | F32: Low
A33: 0.3 | B33: Low Risk | C33: 40 | D33: Research & Development | E33: Yes | F33: Medium
A34: 0.15 | B34: Low Risk | C34: 41 | D34: Research & Development | E34: No | F34: Low | J34: SalaryCategory | K34: Average of AttritionRiskScore
A35: 0.15 | B35: Low Risk | C35: 42 | D35: Sales | E35: No | F35: Low | J35: High | K35: 0.29103448
A36: 0.7 | B36: Medium Risk | C36: 45 | D36: Research & Development | E36: Yes | F36: Low | J36: Low | K36: 0.42759494
A37: 0.35 | B37: Medium Risk | C37: 46 | D37: Research & Development | E37: No | F37: Low | J37: Medium | K37: 0.41828125
A38: 0.5 | B38: High Risk | C38: 47 | D38: Sales | E38: Yes | F38: Low | J38: (blank)
A39: 0.15 | B39: Low Risk | C39: 49 | D39: Sales | E39: No | F39: Low | J39: Grand Total | K39: 0.38312925
A40: 0.75 | B40: Medium Risk | C40: 51 | D40: Research & Development | E40: Yes | F40: Medium
A41: 0.4 | B41: Medium Risk | C41: 52 | D41: Sales | E41: No | F41: Medium
A42: 0.15 | B42: Low Risk | C42: 53 | D42: Research & Development | E42: No | F42: Low
A43: 0.4 | B43: Medium Risk | C43: 54 | D43: Research & Development | E43: No | F43: Low
A44: 0.55 | B44: Medium Risk | C44: 55 | D44: Research & Development | E44: No | F44: Low
A45: 0 | B45: Low Risk | C45: 56 | D45: Sales | E45: No | F45: High
A46: 0.15 | B46: Low Risk | C46: 57 | D46: Research & Development | E46: No | F46: Medium
A47: 0.25 | B47: Low Risk | C47: 58 | D47: Research & Development | E47: No | F47: High | J47: AtriRiskCategory | K47: Count of EmployeeNumber
A48: 0.4 | B48: Medium Risk | C48: 60 | D48: Sales | E48: No | F48: Medium | J48: High Risk | K48: 314
A49: 0.6 | B49: Medium Risk | C49: 61 | D49: Research & Development | E49: No | F49: Medium | J49: Low Risk | K49: 405
A50: 0.5 | B50: High Risk | C50: 62 | D50: Sales | E50: Yes | F50: Medium | J50: Medium Risk | K50: 751
A51: 0.15 | B51: Low Risk | C51: 63 | D51: Research & Development | E51: No | F51: Low | J51: Grand Total | K51: 1470
A52: 0.5 | B52: High Risk | C52: 64 | D52: Research & Development | E52: Yes | F52: Medium
A53: 0.5 | B53: Medium Risk | C53: 65 | D53: Research & Development | E53: Yes | F53: Medium
A54: 0.95 | B54: Medium Risk | C54: 68 | D54: Sales | E54: Yes | F54: Medium
A55: 0.4 | B55: Medium Risk | C55: 70 | D55: Research & Development | E55: Yes | F55: High
A56: 0.5 | B56: Medium Risk | C56: 72 | D56: Sales | E56: Yes | F56: Medium
A57: 0.4 | B57: Medium Risk | C57: 73 | D57: Research & Development | E57: Yes | F57: High
A58: 0.65 | B58: Medium Risk | C58: 74 | D58: Sales | E58: No | F58: High
A59: 0.55 | B59: Medium Risk | C59: 75 | D59: Research & Development | E59: Yes | F59: Medium
A60: 0.35 | B60: Medium Risk | C60: 76 | D60: Research & Development | E60: No | F60: Medium
A61: 0.35 | B61: Medium Risk | C61: 77 | D61: Research & Development | E61: No | F61: Medium
A62: 0.55 | B62: Medium Risk | C62: 78 | D62: Research & Development | E62: Yes | F62: Medium
A63: 0.2 | B63: Low Risk | C63: 79 | D63: Research & Development | E63: No | F63: Low
... A1471: 0.35 | B1471: Medium Risk | C1471: 2068 | D1471: Research & Development | E1471: No | F1471: Medium

Sheet Attrition
G3: Attrition Analysis
B9: 🟦 DEMOGRAPHICS | I9: FINANCIAL | O9: BEHAVIOR
B10: Overal Attrition | C10: Count of Attrition2 | D10: Count of Attrition | I10: Sum of EmployeeCount | J10: Attrition | O10: Count of Attrition | P10: Attrition
B11: No | C11: 1233 | D11: 0.83877551 | I11: SalaryCategory | J11: No | K11: Yes | L11: Grand Total | O11: OverTime | P11: No | Q11: Yes | R11: Grand Total
B12: Yes | C12: 237 | D12: 0.16122449 | I12: High | J12: 0.89195402 | K12: 0.10804598 | L12: 1 | O12: No | P12: 0.89563567 | Q12: 0.10436433 | R12: 1
B13: Grand Total | C13: 1470 | D13: 1 | I13: Low | J13: 0.71392405 | K13: 0.28607595 | L13: 1 | O13: Yes | P13: 0.69471154 | Q13: 0.30528846 | R13: 1
I14: Medium | J14: 0.8796875 | K14: 0.1203125 | L14: 1 | O14: Grand Total | P14: 0.83877551 | Q14: 0.16122449 | R14: 1
B15: Count of Attrition | C15: Attrition | I15: Grand Total | J15: 0.83877551 | K15: 0.16122449 | L15: 1 | O15: Count of Attrition | P15: Attrition
B16: AgeGroup | C16: No | D16: Yes | E16: Grand Total | I16: Insight | O16: WorkLifeBalance | P16: No | Q16: Yes | R16: Grand Total
B17: <25 | C17: 0.60824742 | D17: 0.39175258 | E17: 1 | I17: Attrition is higher in the low salary category (28.6%) than in the medium (12.0%) and high (10.8%) categories. | O17: 2 | P17: 0.83139535 | Q17: 0.16860465 | R17: 1
B18: 25–34 | C18: 0.79783394 | D18: 0.20216606 | E18: 1 | O18: 3 | P18: 0.85778275 | Q18: 0.14221725 | R18: 1
B19: 35–44 | C19: 0.8990099 | D19: 0.1009901 | E19: 1 | O19: 4 | P19: 0.82352941 | Q19: 0.17647059 | R19: 1
B20: 45–54 | C20: 0.89795918 | D20: 0.10204082 | E20: 1 | O20: 1 | P20: 0.6875 | Q20: 0.3125 | R20: 1
B21: 55+ | C21: 0.84057971 | D21: 0.15942029 | E21: 1 | O21: Grand Total | P21: 0.83877551 | Q21: 0.16122449 | R21: 1
B22: Grand Total | C22: 0.83877551 | D22: 0.16122449 | E22: 1 | H22: ORGANIZATIONAL | O22: Insight
H23: Count of EmployeeNumber | I23: Attrition | O23: Attrition is highest at the lowest work-life balance rating (31.2%), but it does not fall steadily as the rating improves: ratings 2, 3 and 4 are between 14% and 18%. Employees with ratings 1 or 2 are 35% of all leavers, so work-life balance is worth monitoring, not a stand-alone predictor.
B24: Count of Attrition | C24: Attrition | H24: JobRole | I24: No | J24: Yes | K24: Grand Total
B25: Gender | C25: No | D25: Yes | E25: Grand Total | H25: Healthcare Representative | I25: 0.93129771 | J25: 0.06870229 | K25: 1 | O25: Count of Attrition | P25: Attrition
B26: Female | C26: 0.85204082 | D26: 0.14795918 | E26: 1 | H26: Human Resources | I26: 0.76923077 | J26: 0.23076923 | K26: 1 | O26: JobSatisfaction | P26: No | Q26: Yes | R26: Grand Total
B27: Male | C27: 0.82993197 | D27: 0.17006803 | E27: 1 | H27: Laboratory Technician | I27: 0.76061776 | J27: 0.23938224 | K27: 1 | O27: 1 | P27: 0.18085969 | Q27: 0.27848101 | R27: 0.19659864
B28: Grand Total | C28: 0.83877551 | D28: 0.16122449 | E28: 1 | H28: Manager | I28: 0.95098039 | J28: 0.049019608 | K28: 1 | O28: 2 | P28: 0.18978102 | Q28: 0.19409283 | R28: 0.19047619
H29: Manufacturing Director | I29: 0.93103448 | J29: 0.068965517 | K29: 1 | O29: 3 | P29: 0.29927007 | Q29: 0.30801688 | R29: 0.30068027
B30: Count of Attrition | C30: Attrition | H30: Research Director | I30: 0.975 | J30: 0.025 | K30: 1 | O30: 4 | P30: 0.33008921 | Q30: 0.21940928 | R30: 0.3122449
B31: MaritalStatus | C31: No | D31: Yes | E31: Grand Total | H31: Research Scientist | I31: 0.8390411 | J31: 0.1609589 | K31: 1 | O31: Grand Total | P31: 1 | Q31: 1 | R31: 1
B32: Divorced | C32: 0.89908257 | D32: 0.10091743 | E32: 1 | H32: Sales Executive | I32: 0.82515337 | J32: 0.17484663 | K32: 1
B33: Married | C33: 0.87518574 | D33: 0.12481426 | E33: 1 | H33: Sales Representative | I33: 0.60240964 | J33: 0.39759036 | K33: 1 | O33: Count of Attrition | P33: Attrition
B34: Single | C34: 0.74468085 | D34: 0.25531915 | E34: 1 | H34: Grand Total | I34: 0.83877551 | J34: 0.16122449 | K34: 1 | O34: EnvironmentSatisfaction | P34: No | Q34: Yes | R34: Grand Total
B35: Grand Total | C35: 0.83877551 | D35: 0.16122449 | E35: 1 | H35: Insight | O35: 1 | P35: 0.74647887 | Q35: 0.25352113 | R35: 1
H36: Attrition is significantly higher among Sales Representative compared to other roles, suggesting that frontline sales positions may face higher stress levels or lower job satisfaction. | O36: 2 | P36: 0.85017422 | Q36: 0.14982578 | R36: 1
O37: 3 | P37: 0.86313466 | Q37: 0.13686534 | R37: 1
H38: Sum of EmployeeCount | I38: Attrition | O38: 4 | P38: 0.86547085 | Q38: 0.13452915 | R38: 1
H39: Department | I39: No | J39: Yes | K39: Grand Total | O39: Grand Total | P39: 0.83877551 | Q39: 0.16122449 | R39: 1
H40: Human Resources | I40: 0.80952381 | J40: 0.19047619 | K40: 1
H41: Research & Development | I41: 0.8616025 | J41: 0.1383975 | K41: 1
H42: Sales | I42: 0.79372197 | J42: 0.20627803 | K42: 1
H43: Grand Total | I43: 0.83877551 | J43: 0.16122449 | K43: 1
C44: RISK MODEL | H44: Insight
B45: Sum of EmployeeCount | C45: Attrition | H45: The Sales department shows the highest attrition rate, indicating potential challenges such as workload pressure or compensation issues. | O45: Count of EmployeeNumber | P45: YearsSinceLastPromotion
B46: RiskCategory | C46: No | D46: Yes | E46: Grand Total | O46: Attrition | P46: 0 | Q46: 1 | R46: 2 | S46: 3 | T46: 4 | U46: 5 | V46: 6 | W46: 7 | X46: 8 | Y46: 9 | Z46: 10 | AA46: 11 | AB46: 12 | AC46: 13 | AD46: 14 | AE46: 15 | AF46: Grand Total
B47: High | C47: 0.52380952 | D47: 0.47619048 | E47: 1 | H47: EarlyLeaver | I47: Count of EarlyLeaver | J47: Count of EarlyLeaver2 | O47: No | P47: 0.32040816 | Q47: 0.20952381 | R47: 0.089795918 | S47: 0.029251701 | T47: 0.038095238 | U47: 0.029251701 | V47: 0.017687075 | W47: 0.040816327 | X47: 0.012244898 | Y47: 0.0088435374 | Z47: 0.0034013605 | AA47: 0.014965986 | AB47: 0.0068027211 | AC47: 0.0054421769 | AD47: 0.0054421769 | AE47: 0.0068027211 | AF47: 0.83877551
B48: Low | C48: 0.94376098 | D48: 0.056239016 | E48: 1 | H48: No | I48: 1395 | J48: 0.94897959 | O48: Yes | P48: 0.074829932 | Q48: 0.033333333 | R48: 0.018367347 | S48: 0.006122449 | T48: 0.0034013605 | U48: 0.0013605442 | V48: 0.0040816327 | W48: 0.010884354 | X48: 0 | Y48: 0.0027210884 | Z48: 0.00068027211 | AA48: 0.0013605442 | AB48: 0 | AC48: 0.0013605442 | AD48: 0.00068027211 | AE48: 0.0020408163 | AF48: 0.16122449
B49: Medium | C49: 0.83848315 | D49: 0.16151685 | E49: 1 | H49: Yes | I49: 75 | J49: 0.051020408 | O49: Grand Total | P49: 0.3952381 | Q49: 0.24285714 | R49: 0.10816327 | S49: 0.03537415 | T49: 0.041496599 | U49: 0.030612245 | V49: 0.021768707 | W49: 0.05170068 | X49: 0.012244898 | Y49: 0.011564626 | Z49: 0.0040816327 | AA49: 0.016326531 | AB49: 0.0068027211 | AC49: 0.0068027211 | AD49: 0.006122449 | AE49: 0.0088435374 | AF49: 1
B50: Grand Total | C50: 0.83877551 | D50: 0.16122449 | E50: 1 | H50: Grand Total | I50: 1470 | J50: 1
H52: Sum of EmployeeCount | I52: EarlyLeaver
H53: Department | I53: No | J53: Yes | K53: Grand Total
H54: Human Resources | I54: 0.93650794 | J54: 0.063492063 | K54: 1 | O54: Count of AttritionRiskScore
H55: Research & Development | I55: 0.95109261 | J55: 0.048907388 | K55: 1 | O55: 1470
H56: Sales | I56: 0.94618834 | J56: 0.053811659 | K56: 1
H57: Grand Total | I57: 0.94897959 | J57: 0.051020408 | K57: 1
H58: early attrition as employees leaving within two years
H60: Count of Attrition | I60: Attrition
H61: JobLevel | I61: No | J61: Yes | K61: Grand Total
H62: 1 | I62: 0.73664825 | J62: 0.26335175 | K62: 1
H63: 2 | I63: 0.90262172 | J63: 0.097378277 | K63: 1
H64: 3 | I64: 0.85321101 | J64: 0.14678899 | K64: 1
H65: 4 | I65: 0.95283019 | J65: 0.047169811 | K65: 1
H66: 5 | I66: 0.92753623 | J66: 0.072463768 | K66: 1
H67: Grand Total | I67: 0.83877551 | J67: 0.16122449 | K67: 1

Sheet Compensation&Pay
AL2: =IF(@[WorkLifeBalance]<=2,1,0)
J5: PAY EQUITY | K5: Gender Pay Gap
C6: Average of MonthlyIncome | I6: Average of MonthlyIncome | J6: Department
C7: 6502.9313 | I7: Gender | J7: Human Resources | K7: Research & Development | L7: Sales | M7: Grand Total
I8: Female | J8: 7264 | K8: 6513.6913 | L8: 6972.127 | M8: 6686.5663
I9: Male | J9: 6371.0233 | K9: 6129.8883 | L9: 6949.6459 | M9: 6380.5079
C10: Income by Job Role | I10: Grand Total | J10: 6654.5079 | K10: 6281.2529 | L10: 6959.1726 | M10: 6502.9313
C11: JobRole | D11: Average of MonthlyIncome
C12: Healthcare Representative | D12: 7528.7634
C13: Human Resources | D13: 4235.75
C14: Laboratory Technician | D14: 3237.1699 | J14: Salary vs Attrition
C15: Manager | D15: 17181.676 | I15: Attrition | J15: Average of MonthlyIncome
C16: Manufacturing Director | D16: 7295.1379 | I16: No | J16: 6832.7397
C17: Research Director | D17: 16033.55 | I17: Yes | J17: 4787.0928
C18: Research Scientist | D18: 3239.9726 | I18: Grand Total | J18: 6502.9313
C19: Sales Executive | D19: 6924.2791
C20: Sales Representative | D20: 2626
C21: Grand Total | D21: 6502.9313 | I21: Salary Growth Proxy
I22: JobLevel | J22: Average of PercentSalaryHike
I23: 1 | J23: 15.305709
C24: Income by Department | I24: 2 | J24: 15.205993
C25: Department | D25: Average of MonthlyIncome | I25: 3 | J25: 15.197248
C26: Human Resources | D26: 6654.5079 | I26: 4 | J26: 15.292453
C27: Research & Development | D27: 6281.2529 | I27: 5 | J27: 14.391304
C28: Sales | D28: 6959.1726 | I28: Grand Total | J28: 15.209524
C29: Grand Total | D29: 6502.9313
K32: Salary vs Performance
C33: TotalWorkingYears | D33: Average of MonthlyIncome | G33: Income vs Experience | K33: PerformanceRating | L33: Average of MonthlyIncome
C34: 0 | D34: 1523.6364 | K34: 3 | L34: 6537.2741
C35: 1 | D35: 2208.8272 | K35: 4 | L35: 6313.8938
C36: 2 | D36: 2650.1935 | K36: Grand Total | L36: 6502.9313
C37: 3 | D37: 2781.0476
C38: 4 | D38: 3614.4286
C39: 5 | D39: 3476.6591
C40: 6 | D40: 4215.256
C41: 7 | D41: 4171.3086
C42: 8 | D42: 4209.2524
C43: 9 | D43: 6623.4062
C44: 10 | D44: 6019.7673
C45: 11 | D45: 5669.3333
C46: 12 | D46: 6020.5833
C47: 13 | D47: 6254.9167
C48: 14 | D48: 7362.2581
... C73: 40 | D73: 14779
C74: Grand Total | D74: 6502.9313

Sheet Employee Experience
C6: Count of Attrition | D6: Attrition | I6: EnvironmentSatisfaction | J6: Sum of EmployeeCount | M6: WorkLifeBalance | N6: Sum of EmployeeCount
C7: JobInvolvement | D7: No | E7: Yes | F7: Grand Total | I7: 1 | J7: 0.19319728 | M7: 1 | N7: 0.054421769
C8: 1 | D8: 0.6626506 | E8: 0.3373494 | F8: 1 | I8: 2 | J8: 0.1952381 | M8: 2 | N8: 0.23401361
C9: 2 | D9: 0.81066667 | E9: 0.18933333 | F9: 1 | I9: 3 | J9: 0.30816327 | M9: 3 | N9: 0.60748299
C10: 3 | D10: 0.85599078 | E10: 0.14400922 | F10: 1 | I10: 4 | J10: 0.30340136 | M10: 4 | N10: 0.10408163
C11: 4 | D11: 0.90972222 | E11: 0.090277778 | F11: 1 | I11: Grand Total | J11: 1 | M11: Grand Total | N11: 1
C12: Grand Total | D12: 0.83877551 | E12: 0.16122449 | F12: 1
C16: Count of Attrition | D16: Attrition | I16: JobInvolvement | J16: Sum of EmployeeCount | M16: TrainingTimesLastYear | N16: Sum of EmployeeCount
C17: JobSatisfaction | D17: No | E17: Yes | F17: Grand Total | I17: 1 | J17: 0.056462585 | M17: 0 | N17: 0.036734694
C18: 1 | D18: 0.7716263 | E18: 0.2283737 | F18: 1 | I18: 2 | J18: 0.25510204 | M18: 1 | N18: 0.04829932
C19: 2 | D19: 0.83571429 | E19: 0.16428571 | F19: 1 | I19: 3 | J19: 0.59047619 | M19: 2 | N19: 0.37210884
C20: 3 | D20: 0.83484163 | E20: 0.16515837 | F20: 1 | I20: 4 | J20: 0.097959184 | M20: 3 | N20: 0.33401361
C21: 4 | D21: 0.88671024 | E21: 0.11328976 | F21: 1 | I21: Grand Total | J21: 1 | M21: 4 | N21: 0.083673469
C22: Grand Total | D22: 0.83877551 | E22: 0.16122449 | F22: 1 | M22: 5 | N22: 0.080952381
M23: 6 | N23: 0.044217687
M24: Grand Total | N24: 1
C25: JobSatisfaction | D25: Count of EmployeeNumber
C26: 1 | D26: 0.19659864 | I26: TrainingTimesLastYear | J26: Average of JobSatisfaction
C27: 2 | D27: 0.19047619 | I27: 0 | J27: 2.962963
C28: 3 | D28: 0.30068027 | I28: 1 | J28: 2.6619718
C29: 4 | D29: 0.3122449 | I29: 2 | J29: 2.7568556
C30: Grand Total | D30: 1 | I30: 3 | J30: 2.6435845
I31: 4 | J31: 2.8455285
I32: 5 | J32: 2.6806723
I33: 6 | J33: 2.8769231
I34: Grand Total | J34: 2.7285714

Sheet Performance KPIs
C6: Performance Rating Distribution | H6: Performance vs Salary
C7: PerformanceRating | D7: Count of EmployeeNumber | H7: PerformanceRating | I7: Average of MonthlyIncome
C8: 3 | D8: 0.8462585 | H8: 3 | I8: 6537.2741
C9: 4 | D9: 0.1537415 | H9: 4 | I9: 6313.8938
C10: Grand Total | D10: 1 | H10: Grand Total | I10: 6502.9313
C13: Performance vs Attrition | H13: Performance vc Salary Hike
C14: Count of EmployeeNumber | D14: Attrition | H14: PerformanceRating | I14: Average of PercentSalaryHike
C15: PerformanceRating | D15: No | E15: Yes | F15: Grand Total | H15: 3 | I15: 14.003215
C16: 3 | D16: 1044 | E16: 200 | F16: 1244 | H16: 4 | I16: 21.849558
C17: 4 | D17: 189 | E17: 37 | F17: 226 | H17: Grand Total | I17: 15.209524
C18: Grand Total | D18: 1233 | E18: 237 | F18: 1470
C23: JobInvolvement | D23: Average of PerformanceRating
C24: 1 | D24: 3.2048193 | H24: YearsSinceLastPromotion | I24: Average of PerformanceRating
C25: 2 | D25: 3.1546667 | H25: 0 | I25: 3.1652324
C26: 3 | D26: 3.1509217 | H26: 1 | I26: 3.1344538
C27: 4 | D27: 3.1388889 | H27: 2 | I27: 3.1257862
C28: Grand Total | D28: 3.1537415 | H28: 3 | I28: 3.1538462
H29: 4 | I29: 3.1311475
H30: 5 | I30: 3.2444444
H31: 6 | I31: 3.125
H32: 7 | I32: 3.1447368
H33: 8 | I33: 3.2222222
H34: 9 | I34: 3
H35: 10 | I35: 3.1666667
H36: 11 | I36: 3.3333333
H37: 12 | I37: 3.2
H38: 13 | I38: 3.1
H39: 14 | I39: 3.2222222
H40: 15 | I40: 3.1538462
H41: Grand Total | I41: 3.1537415

Sheet Career Growth & Mobility
F4: Internal Mobility | J4: External Mobility
F5: Average of YearsInCurrentRole | J5: NumCompaniesWorked | K5: Count of EmployeeNumber
C6: Promotion Lag | F6: 4.2292517 | J6: 0 | K6: 197
C7: JobLevel | D7: Average of YearsSinceLastPromotion | J7: 1 | K7: 521
C8: 1 | D8: 1.1933702 | J8: 2 | K8: 146
C9: 2 | D9: 1.8857678 | J9: 3 | K9: 159
C10: 3 | D10: 3.353211 | J10: 4 | K10: 139
C11: 4 | D11: 4.8396226 | J11: 5 | K11: 63
C12: 5 | D12: 4.5942029 | J12: 6 | K12: 70
C13: Grand Total | D13: 2.1877551 | J13: 7 | K13: 74
J14: 8 | K14: 49
J15: 9 | K15: 52
J16: Grand Total | K16: 1470
D18: Tenure vs Promotion | J18: Career Stability vs Attrition
C19: YearsAtCompany | D19: Average of YearsSinceLastPromotion | J19: Count of EmployeeNumber | K19: Attrition
C20: 0 | D20: 0 | J20: YearsSinceLastPromotion | K20: No | L20: Yes | M20: Grand Total
C21: 1 | D21: 0.076023392 | J21: 0 | K21: 471 | L21: 110 | M21: 581
C22: 2 | D22: 1.6771654 | J22: 1 | K22: 308 | L22: 49 | M22: 357
C23: 3 | D23: 0.703125 | J23: 2 | K23: 132 | L23: 27 | M23: 159
C24: 4 | D24: 0.75454545 | J24: 3 | K24: 43 | L24: 9 | M24: 52
C25: 5 | D25: 0.76020408 | J25: 4 | K25: 56 | L25: 5 | M25: 61
C26: 6 | D26: 0.73684211 | J26: 5 | K26: 43 | L26: 2 | M26: 45
C27: 7 | D27: 2.7444444 | J27: 6 | K27: 26 | L27: 6 | M27: 32
C28: 8 | D28: 3.225 | J28: 7 | K28: 60 | L28: 16 | M28: 76
C29: 9 | D29: 3.0365854 | J29: 8 | K29: 18 | M29: 18
C30: 10 | D30: 3.0833333 | J30: 9 | K30: 13 | L30: 4 | M30: 17
C31: 11 | D31: 4.0625 | J31: 10 | K31: 5 | L31: 1 | M31: 6
C32: 12 | D32: 4.3571429 | J32: 11 | K32: 22 | L32: 2 | M32: 24
C33: 13 | D33: 4.5416667 | J33: 12 | K33: 10 | M33: 10
C34: 14 | D34: 4.5555556 | J34: 13 | K34: 8 | L34: 2 | M34: 10
C35: 15 | D35: 5.1 | J35: 14 | K35: 8 | L35: 1 | M35: 9
C36: 16 | D36: 4.75 | J36: 15 | K36: 10 | L36: 3 | M36: 13
C37: 17 | D37: 8.4444444 | J37: Grand Total | K37: 1233 | L37: 237 | M37: 1470
C38: 18 | D38: 5.6923077
C39: 19 | D39: 8.3636364
C40: 20 | D40: 6.2962963
C41: 21 | D41: 8.5714286
C42: 22 | D42: 7.9333333 | J42: Manager Stability
C43: 23 | D43: 14 | J43: Count of EmployeeNumber | K43: Attrition
C44: 24 | D44: 7 | J44: YearsWithCurrManager | K44: No | L44: Yes | M44: Grand Total
C45: 25 | D45: 6 | J45: 0 | K45: 178 | L45: 85 | M45: 263
C46: 26 | D46: 4.75 | J46: 1 | K46: 65 | L46: 11 | M46: 76
C47: 27 | D47: 14 | J47: 2 | K47: 294 | L47: 50 | M47: 344
C48: 29 | D48: 11 | J48: 3 | K48: 123 | L48: 19 | M48: 142
C49: 30 | D49: 12 | J49: 4 | K49: 87 | L49: 11 | M49: 98
C50: 31 | D50: 9 | J50: 5 | K50: 27 | L50: 4 | M50: 31
C51: 32 | D51: 9.6666667 | J51: 6 | K51: 25 | L51: 4 | M51: 29
C52: 33 | D52: 8.4 | J52: 7 | K52: 185 | L52: 31 | M52: 216
C53: 34 | D53: 1 | J53: 8 | K53: 97 | L53: 10 | M53: 107
C54: 36 | D54: 3 | J54: 9 | K54: 58 | L54: 6 | M54: 64
C55: 37 | D55: 1 | J55: 10 | K55: 24 | L55: 3 | M55: 27
C56: 40 | D56: 15 | J56: 11 | K56: 21 | L56: 1 | M56: 22
C57: Grand Total | D57: 2.1877551 | J57: 12 | K57: 18 | M57: 18
J58: 13 | K58: 14 | M58: 14
J59: 14 | K59: 3 | L59: 2 | M59: 5
J60: 15 | K60: 5 | M60: 5
J61: 16 | K61: 2 | M61: 2
J62: 17 | K62: 7 | M62: 7
J63: Grand Total | K63: 1233 | L63: 237 | M63: 1470

Sheet workforce Structure
C6: Workforce Distribution by Department | I6: Organizational Hierarchy
C7: Department | D7: Count of EmployeeNumber | I7: JobLevel | J7: Count of EmployeeNumber
C8: Human Resources | D8: 63 | I8: Entry / Junior | J8: 543
C9: Research & Development | D9: 961 | I9: Intermediate | J9: 534
C10: Sales | D10: 446 | I10: Experienced | J10: 218
C11: Grand Total | D11: 1470 | I11: Senior/Manager | J11: 106
I12: Executive | J12: 69
I13: Grand Total | J13: 1470
C16: Workforce Distribution by Job Role | I16: Overtime Distributions
C17: JobRole | D17: Count of EmployeeNumber | I17: Count of EmployeeNumber | J17: OverTime
C18: Healthcare Representative | D18: 131 | I18: Department | J18: No | K18: Yes | L18: Grand Total
C19: Human Resources | D19: 52 | I19: Human Resources | J19: 0.73015873 | K19: 0.26984127 | L19: 1
C20: Laboratory Technician | D20: 259 | I20: Research & Development | J20: 0.71800208 | K20: 0.28199792 | L20: 1
C21: Manager | D21: 102 | I21: Sales | J21: 0.71300448 | K21: 0.28699552 | L21: 1
C22: Manufacturing Director | D22: 145 | I22: Grand Total | J22: 0.7170068 | K22: 0.2829932 | L22: 1
C23: Research Director | D23: 80
C24: Research Scientist | D24: 292
C25: Sales Executive | D25: 326
C26: Sales Representative | D26: 83
C27: Grand Total | D27: 1470
C30: Business Travel Structure | I30: Work Structure vs Attrition
C31: BusinessTravel | D31: Count of EmployeeNumber | I31: Count of EmployeeNumber | J31: Attrition
C32: Non-Travel | D32: 150 | I32: OverTime | J32: No | K32: Yes | L32: Grand Total
C33: Travel_Frequently | D33: 277 | I33: No | J33: 944 | K33: 110 | L33: 1054
C34: Travel_Rarely | D34: 1043 | I34: Yes | J34: 289 | K34: 127 | L34: 416
C35: Grand Total | D35: 1470 | I35: Grand Total | J35: 1233 | K35: 237 | L35: 1470

Sheet Training & Development
C6: Average Training Sessions | I6: Training vs Performance
C7: Average of TrainingTimesLastYear | I7: TrainingTimesLastYear | J7: Average of PerformanceRating
C8: 2.7993197 | I8: 0 | J8: 3.1851852
I9: 1 | J9: 3.1267606
I10: 2 | J10: 3.1627057
I11: 3 | J11: 3.1507128
I12: 4 | J12: 3.1300813
I13: 5 | J13: 3.1596639
I14: 6 | J14: 3.1384615
I15: Grand Total | J15: 3.1537415
C17: Training vs Job Satisfaction
C18: TrainingTimesLastYear | D18: Average of JobSatisfaction | I18: Training vs Attrition
C19: 0 | D19: 2.962963 | I19: Count of EmployeeNumber | J19: Attrition
C20: 1 | D20: 2.6619718 | I20: TrainingTimesLastYear | J20: No | K20: Yes | L20: Grand Total
C21: 2 | D21: 2.7568556 | I21: 0 | J21: 0.72222222 | K21: 0.27777778 | L21: 1
C22: 3 | D22: 2.6435845 | I22: 1 | J22: 0.87323944 | K22: 0.12676056 | L22: 1
C23: 4 | D23: 2.8455285 | I23: 2 | J23: 0.82084095 | K23: 0.17915905 | L23: 1
C24: 5 | D24: 2.6806723 | I24: 3 | J24: 0.85947047 | K24: 0.14052953 | L24: 1
C25: 6 | D25: 2.8769231 | I25: 4 | J25: 0.78861789 | K25: 0.21138211 | L25: 1
C26: Grand Total | D26: 2.7285714 | I26: 5 | J26: 0.88235294 | K26: 0.11764706 | L26: 1
I27: 6 | J27: 0.90769231 | K27: 0.092307692 | L27: 1
I28: Grand Total | J28: 0.83877551 | K28: 0.16122449 | L28: 1

Sheet Workload & Burnout
C6: Overtime vs Attrition | K6: Work-Life Balance vs Attrition
C7: Count of EmployeeNumber | D7: Attrition | K7: Count of EmployeeNumber | L7: Attrition
C8: OverTime | D8: No | E8: Yes | F8: Grand Total | K8: WorkLifeBalance | L8: No | M8: Yes | N8: Grand Total
C9: No | D9: 944 | E9: 110 | F9: 1054 | K9: 1 | L9: 0.6875 | M9: 0.3125 | N9: 1
C10: Yes | D10: 289 | E10: 127 | F10: 416 | K10: 2 | L10: 0.83139535 | M10: 0.16860465 | N10: 1
C11: Grand Total | D11: 1233 | E11: 237 | F11: 1470 | K11: 3 | L11: 0.85778275 | M11: 0.14221725 | N11: 1
K12: 4 | L12: 0.82352941 | M12: 0.17647059 | N12: 1
K13: Grand Total | L13: 0.83877551 | M13: 0.16122449 | N13: 1
C16: Overtime vs Job Satisfaction | K16: Overtime vs Environment Satisfaction
C17: OverTime | D17: Average of JobSatisfaction | K17: OverTime | L17: Average of EnvironmentSatisfaction
C18: No | D18: 2.711575 | K18: No | L18: 2.6736243
C19: Yes | D19: 2.7716346 | K19: Yes | L19: 2.84375
C20: Grand Total | D20: 2.7285714 | K20: Grand Total | L20: 2.7217687
C24: Years in Current Role vs Attrition | K24: Job Involvement vs Work-Life Balance
C25: Count of EmployeeNumber | D25: Attrition | K25: JobInvolvement | L25: Average of WorkLifeBalance
C26: YearsInCurrentRole | D26: No | E26: Yes | F26: Grand Total | K26: 1 | L26: 2.7349398
C27: 0 | D27: 0.70081967 | E27: 0.29918033 | F27: 1 | K27: 2 | L27: 2.7893333
C28: 1 | D28: 0.80701754 | E28: 0.19298246 | F28: 1 | K28: 3 | L28: 2.7569124
C29: 2 | D29: 0.8172043 | E29: 0.1827957 | F29: 1 | K29: 4 | L29: 2.7291667
C30: 3 | D30: 0.88148148 | E30: 0.11851852 | F30: 1 | K30: Grand Total | L30: 2.7612245
C31: 4 | D31: 0.85576923 | E31: 0.14423077 | F31: 1
C32: 5 | D32: 0.97222222 | E32: 0.027777778 | F32: 1
C33: 6 | D33: 0.94594595 | E33: 0.054054054 | F33: 1
C34: 7 | D34: 0.86036036 | E34: 0.13963964 | F34: 1
C35: 8 | D35: 0.92134831 | E35: 0.078651685 | F35: 1
C36: 9 | D36: 0.91044776 | E36: 0.089552239 | F36: 1
C37: 10 | D37: 0.93103448 | E37: 0.068965517 | F37: 1
C38: 11 | D38: 1 | E38: 0 | F38: 1
C39: 12 | D39: 0.9 | E39: 0.1 | F39: 1
C40: 13 | D40: 0.92857143 | E40: 0.071428571 | F40: 1
C41: 14 | D41: 0.90909091 | E41: 0.090909091 | F41: 1
C42: 15 | D42: 0.75 | E42: 0.25 | F42: 1
C43: Grand Total | D43: 0.83733699 | E43: 0.16266301 | F43: 1

Sheet KPIs_overview
B1: Metric | C1: Value | D1: Interpretation | E1: Insight | F1: Column1
B2: Total Employees | C2: =COUNTA(HR_Data[EmployeeNumber]) -> 1470
B3: Attrition Count | C3: =COUNTIF(HR_Data[Attrition],"Yes") -> 237
B4: Attrition Rate | C4: =ROUND(COUNTIF(HR_Data[Attrition],"Yes") / COUNTA(HR_Data[EmployeeNumber]),3) -> 0.161 | D4: Moderate attrition, requires investigation in departments with high workload | E4: Higher attrition observed among employees with lower salaries
B5: Attrition (OverTime Yes) | C5: =COUNTIFS(HR_Data[Attrition],"Yes",HR_Data[OverTime],"Yes")/COUNTIF(HR_Data[OverTime],"Yes") -> 0.30528846
B6: Attrition (OverTime No) | C6: =COUNTIFS(HR_Data[Attrition],"Yes",HR_Data[OverTime],"No")/COUNTIF(HR_Data[OverTime],"No") -> 0.10436433
B7: Avg Salary | C7: =AVERAGE(HR_Data[MonthlyIncome]) -> 6502.9313
B8: Median Salary | C8: =MEDIAN(HR_Data[MonthlyIncome]) -> 4919
B9: Min Salary | C9: =MIN(HR_Data[MonthlyIncome]) -> 1009
B10: Max Salary | C10: =MAX(HR_Data[MonthlyIncome]) -> 19999
B11: Avg Age | C11: =AVERAGE(HR_Data[Age]) -> 36.92381
B12: Avg Years at Company | C12: =AVERAGE(HR_Data[YearsAtCompany]) -> 7.0081633
B13: Avg Years at Current Role | C13: =AVERAGE(HR_Data[YearsInCurrentRole]) -> 4.2292517
B14: OverTime Rate | C14: =COUNTIF(HR_Data[OverTime],"Yes")/COUNTA(HR_Data[EmployeeNumber]) -> 0.2829932

Sheet Findings
A1: Findings from the IBM HR data (1,470 employees)
A2: Overall attrition is 16.1% (237 of 1,470 employees). This is a public sample dataset, so the results describe this dataset only and show associations, not causes.
A3: What goes with higher attrition
A4: Overtime: 30.5% attrition with overtime against 10.4% without, and the gap appears in every department.
A5: Tenure: 34.9% in the first two years, 15.5% at 2 to 5 years, 12.3% at 6 to 10 years and 8.1% after ten years.
A6: Pay: leavers earned less on average (about 4,800 against 6,800 monthly income). In the low salary category attrition is 28.6%, against 12.0% (medium) and 10.8% (high).
A7: Job involvement: 33.7% attrition at the lowest rating against 9.0% at the highest.
A8: Job satisfaction: 22.8% at the lowest rating against 11.3% at the highest.
A9: Environment satisfaction: 25.4% at the lowest rating against 13.5% at the highest.
A10: Work-life balance: 31.2% at the lowest rating (80 employees), but only 14% to 18% at ratings 2 to 4, so the effect sits mainly in the lowest group.
A11: Time with the current manager: leavers had spent 2.9 years with their manager, stayers 4.4 years.
A12: Departments and roles
... A25: Small groups (HR 63 employees, 0 to 2 years of tenure 215 employees) need careful reading. Salary band cut-offs differ between the Excel dashboard (3,000 and 7,000) and the SQL analysis (4,000 and 8,000), so band percentages differ slightly.
